{"ticker":"ASHGEQ","name":"Ashburton Global 1200 ETF","provider":"Ashburton (FNB)","category":"Global Equity","ter":0.0075,"dividend":"Reinvests","index":"S&P Global 1200 Index","index_rules":"Composite of 7 regional indices covering 31 countries and ~1,200 companies.","rebalancing":"Quarterly","top_holdings":[{"name":"Apple","weight":4.5},{"name":"Microsoft","weight":4},{"name":"Nvidia","weight":3.8},{"name":"Amazon","weight":2.6},{"name":"Meta","weight":1.8},{"name":"Alphabet A","weight":1.4},{"name":"Berkshire Hathaway","weight":1.1},{"name":"ASML","weight":0.9},{"name":"Eli Lilly","weight":0.9},{"name":"Novo Nordisk","weight":0.8}],"has_price_data":false,"last_updated":"2026-04-26 16:29:12"}
