{"ticker":"STXEME","name":"Satrix MSCI EM ESG Enhanced","provider":"Satrix","ee_aliases":["Satrix EM ESG"],"category":"Global Equity","ter":0.0038,"dividend":"Fund does not distribute. Last four distributions: N/A","index":"MSCI EM ESG Enhanced Focus CTB Index","index_rules":"The Satrix MSCI EM ESG Enhanced Feeder ETF is an index tracking fund registered as a Collective Investment Scheme, and is listed on the Johannesburg Stock Exchange as an Exchange Traded Fund. The mandate of the Satrix MSCI EM ESG Enhanced Feeder Portfolio (‘Satrix MSCI EM ESG Enhanced Feeder ETF”) is to track, as closely as possible, the value of the MSCI EM ESG Enhanced Focus CTB Index in ZAR. The MSCI EM ESG Enhanced Focus CTB Index measures the performance of emerging market companies that screens out controversial business areas and gives greater weighting to companies with higher environmental, social and governance (ESG) scores. To replicate the index performance the Satrix MSCI EM ESG Enhanced Feeder ETF invests in the iShares MSCI EM ESG Enhanced UCITS ETF (the underlying fund). The investment objective of the underlying fund is to provide investors with a total return, taking into account both capital and income returns, which reflects the return of the MSCI EM ESG Enhanced Focus CTB Index. Investors should note that the performance of the Satrix MSCI EM ESG Enhanced Feeder ETF relative to its benchmark may be affected on a day to day basis as a result of transactions, exchange rates and differing pricing points.","rebalancing":null,"fund_type":"Passive ETF","mdd_updated":"28 February 2026 (Understanding your MDD)","top_holdings":[{"name":"Taiwan Semiconductor Manufacturing (13.50%)","weight":null},{"name":"Samsung Electronics Ltd (5.87%)","weight":null},{"name":"Sk Hynix Inc (3.59%)","weight":null},{"name":"Tencent Holdings Ltd (3.50%)","weight":null},{"name":"Alibaba Group Holding Ltd (2.62%)","weight":null},{"name":"Reliance Industries Ltd (1.18%)","weight":null},{"name":"Samsung Electronics Non Voting Pre (1.17%)","weight":null},{"name":"China Construction Bank Corp H (1.15%)","weight":null},{"name":"Hdfc Bank Ltd (1.10%)","weight":null},{"name":"Usd Cash (1.02%)","weight":null}],"has_price_data":true,"last_updated":"2026-05-10 19:16:43","metrics":{"total_return":0.744378,"cagr":0.104945,"ann_vol":0.17257,"sharpe":0.1865,"sortino":0.2795,"calmar":0.4178,"omega":1.0329,"max_drawdown":-0.2512,"var_95":-0.015858,"cvar_95":-0.022167,"ytd_return":0.197633,"return_1m":0.122792,"return_3m":0.146221,"return_6m":0.178905,"return_1y":0.3715,"return_3y":0.613848,"n_trading_days":1405,"start_date":"2020-09-11","end_date":"2026-05-08"},"prices":[{"date":"2020-09-11","open":4532.48,"high":4534.9102,"low":4532.48,"close":4534.9102,"volume":0,"adjusted":4534.9102,"daily_return":null,"cum_return":0},{"date":"2020-09-18","open":4577.4302,"high":4614.5,"low":4484.52,"close":4484.52,"volume":0,"adjusted":4484.52,"daily_return":-0.011112,"cum_return":-0.011112},{"date":"2020-09-25","open":4525.3599,"high":4562.27,"low":4481.8799,"close":4498.6699,"volume":0,"adjusted":4498.6699,"daily_return":0.003155,"cum_return":-0.007991},{"date":"2020-10-02","open":4582.2402,"high":4582.2402,"low":4474.46,"close":4474.46,"volume":0,"adjusted":4474.46,"daily_return":-0.005382,"cum_return":-0.01333},{"date":"2020-10-09","open":4517.4902,"high":4650.0298,"low":4517.4902,"close":4650.0298,"volume":0,"adjusted":4650.0298,"daily_return":0.039238,"cum_return":0.025385},{"date":"2020-10-16","open":4695.5498,"high":4695.5498,"low":4653.75,"close":4656.8999,"volume":0,"adjusted":4656.8999,"daily_return":0.001477,"cum_return":0.0269},{"date":"2020-10-23","open":4648.8301,"high":4669.6099,"low":4593.8501,"close":4624.2002,"volume":0,"adjusted":4624.2002,"daily_return":-0.007022,"cum_return":0.019689},{"date":"2020-10-30","open":4561.0098,"high":4581.73,"low":4477.3799,"close":4477.3799,"volume":0,"adjusted":4477.3799,"daily_return":-0.03175,"cum_return":-0.012686},{"date":"2020-11-06","open":4554.3599,"high":4627.3701,"low":4500.7402,"close":4603.3301,"volume":0,"adjusted":4603.3301,"daily_return":0.02813,"cum_return":0.015087},{"date":"2020-11-13","open":4701.1499,"high":4701.1499,"low":4620.4302,"close":4655.5698,"volume":0,"adjusted":4655.5698,"daily_return":0.011348,"cum_return":0.026607},{"date":"2020-11-20","open":4630.6001,"high":4671.8799,"low":4630.6001,"close":4647.1699,"volume":0,"adjusted":4647.1699,"daily_return":-0.001804,"cum_return":0.024755},{"date":"2020-11-27","open":4729.1899,"high":4729.1899,"low":4661.48,"close":4726.9399,"volume":0,"adjusted":4726.9399,"daily_return":0.017165,"cum_return":0.042345},{"date":"2020-12-04","open":4707.3901,"high":4775.1699,"low":4667.5298,"close":4775.1699,"volume":0,"adjusted":4775.1699,"daily_return":0.010203,"cum_return":0.05298},{"date":"2020-12-11","open":4756.0298,"high":4763.3398,"low":4714.0898,"close":4763.3398,"volume":0,"adjusted":4763.3398,"daily_return":-0.002477,"cum_return":0.050371},{"date":"2020-12-18","open":4702.04,"high":4702.04,"low":4616.3701,"close":4616.3701,"volume":0,"adjusted":4616.3701,"daily_return":-0.030854,"cum_return":0.017963},{"date":"2020-12-24","open":4648.3501,"high":4648.3501,"low":4583.6499,"close":4583.6499,"volume":0,"adjusted":4583.6499,"daily_return":-0.007088,"cum_return":0.010748},{"date":"2020-12-31","open":4590.9902,"high":4757.98,"low":4590.9902,"close":4757.98,"volume":0,"adjusted":4757.98,"daily_return":0.038033,"cum_return":0.049189},{"date":"2021-01-08","open":4789.6899,"high":5183.1499,"low":4789.6899,"close":5183.1499,"volume":0,"adjusted":5183.1499,"daily_return":0.089359,"cum_return":0.142944},{"date":"2021-01-15","open":5247.2002,"high":5247.2002,"low":5192.8301,"close":5192.8301,"volume":0,"adjusted":5192.8301,"daily_return":0.001868,"cum_return":0.145079},{"date":"2021-01-22","open":5173.5698,"high":5281.2002,"low":5173.5698,"close":5281.2002,"volume":0,"adjusted":5281.2002,"daily_return":0.017018,"cum_return":0.164566},{"date":"2021-01-29","open":5399.77,"high":5399.77,"low":5031.3101,"close":5031.3101,"volume":0,"adjusted":5031.3101,"daily_return":-0.047317,"cum_return":0.109462},{"date":"2021-02-05","open":5158.75,"high":5258.1299,"low":5158.75,"close":5214.0698,"volume":0,"adjusted":5214.0698,"daily_return":0.036324,"cum_return":0.149763},{"date":"2021-02-12","open":5222.29,"high":5251.2202,"low":5214.3301,"close":5214.3301,"volume":0,"adjusted":5214.3301,"daily_return":0.00005,"cum_return":0.14982},{"date":"2021-02-19","open":5170.8198,"high":5326.3101,"low":5170.8198,"close":5242.4902,"volume":0,"adjusted":5242.4902,"daily_return":0.005401,"cum_return":0.15603},{"date":"2021-02-26","open":5149.46,"high":5149.46,"low":5019.4102,"close":5061.4102,"volume":0,"adjusted":5061.4102,"daily_return":-0.034541,"cum_return":0.116099},{"date":"2021-03-05","open":5067,"high":5157.3101,"low":5067,"close":5157.3101,"volume":0,"adjusted":5157.3101,"daily_return":0.018947,"cum_return":0.137246},{"date":"2021-03-12","open":5062.3398,"high":5083.6802,"low":5034.2202,"close":5047.48,"volume":0,"adjusted":5047.48,"daily_return":-0.021296,"cum_return":0.113028},{"date":"2021-03-19","open":5004.8599,"high":5010.5298,"low":4927,"close":4927,"volume":0,"adjusted":4927,"daily_return":-0.023869,"cum_return":0.08646},{"date":"2021-03-26","open":4881.2402,"high":4928.1299,"low":4844.6099,"close":4928.1299,"volume":0,"adjusted":4928.1299,"daily_return":0.000229,"cum_return":0.086709},{"date":"2021-04-01","open":4922.4502,"high":4942.02,"low":4877.3198,"close":4907.5,"volume":0,"adjusted":4907.5,"daily_return":-0.004186,"cum_return":0.08216},{"date":"2021-04-09","open":4916.8398,"high":4916.8398,"low":4872.8398,"close":4876.8398,"volume":0,"adjusted":4876.8398,"daily_return":-0.006248,"cum_return":0.075399},{"date":"2021-04-16","open":4840.5,"high":4847.0098,"low":4773.8501,"close":4847.0098,"volume":0,"adjusted":4847.0098,"daily_return":-0.006117,"cum_return":0.068822},{"date":"2021-04-23","open":4820.52,"high":4855.9102,"low":4779.8501,"close":4855.9102,"volume":0,"adjusted":4855.9102,"daily_return":0.001836,"cum_return":0.070784},{"date":"2021-04-30","open":4865.3799,"high":4907.2598,"low":4865.3799,"close":4907.2598,"volume":0,"adjusted":4907.2598,"daily_return":0.010575,"cum_return":0.082107},{"date":"2021-05-07","open":4869.6201,"high":4869.6201,"low":4766.8799,"close":4766.8799,"volume":0,"adjusted":4766.8799,"daily_return":-0.028607,"cum_return":0.051152},{"date":"2021-05-14","open":4747.8301,"high":4747.8301,"low":4579.29,"close":4644.5298,"volume":0,"adjusted":4644.5298,"daily_return":-0.025667,"cum_return":0.024172},{"date":"2021-05-21","open":4648.3198,"high":4705.3901,"low":4648.3198,"close":4671.27,"volume":0,"adjusted":4671.27,"daily_return":0.005757,"cum_return":0.030069},{"date":"2021-05-28","open":4652.6802,"high":4728.6099,"low":4652.6802,"close":4728.6099,"volume":0,"adjusted":4728.6099,"daily_return":0.012275,"cum_return":0.042713},{"date":"2021-06-04","open":4705.7998,"high":4830.1602,"low":4705.7998,"close":4709.7402,"volume":0,"adjusted":4709.7402,"daily_return":-0.003991,"cum_return":0.038552},{"date":"2021-06-11","open":4715.21,"high":4782.4502,"low":4715.21,"close":4782.4502,"volume":0,"adjusted":4782.4502,"daily_return":0.015438,"cum_return":0.054585},{"date":"2021-06-18","open":4791.1099,"high":4927.5698,"low":4791.1099,"close":4927.5698,"volume":0,"adjusted":4927.5698,"daily_return":0.030344,"cum_return":0.086586},{"date":"2021-06-25","open":4879.1602,"high":4938.75,"low":4879.1602,"close":4928.6099,"volume":0,"adjusted":4928.6099,"daily_return":0.000211,"cum_return":0.086815},{"date":"2021-07-02","open":4973.8599,"high":5017.6499,"low":4925.2202,"close":4925.2202,"volume":0,"adjusted":4925.2202,"daily_return":-0.000688,"cum_return":0.086068},{"date":"2021-07-09","open":4900.9102,"high":4919.4399,"low":4776.5098,"close":4776.5098,"volume":0,"adjusted":4776.5098,"daily_return":-0.030194,"cum_return":0.053276},{"date":"2021-07-16","open":4868.8101,"high":4986.21,"low":4868.8101,"close":4911.4902,"volume":0,"adjusted":4911.4902,"daily_return":0.028259,"cum_return":0.08304},{"date":"2021-07-23","open":4863.3301,"high":4957.02,"low":4863.3301,"close":4946.75,"volume":0,"adjusted":4946.75,"daily_return":0.007179,"cum_return":0.090815},{"date":"2021-07-30","open":4835.5298,"high":4835.5298,"low":4719.2202,"close":4767.27,"volume":0,"adjusted":4767.27,"daily_return":-0.036282,"cum_return":0.051238},{"date":"2021-08-06","open":4744.8901,"high":4841.77,"low":4740.2598,"close":4841.77,"volume":0,"adjusted":4841.77,"daily_return":0.015627,"cum_return":0.067666},{"date":"2021-08-13","open":4918.7798,"high":4918.7798,"low":4811.9199,"close":4811.9199,"volume":0,"adjusted":4811.9199,"daily_return":-0.006165,"cum_return":0.061084},{"date":"2021-08-20","open":4793.5801,"high":4824.2998,"low":4785.3198,"close":4788.9502,"volume":0,"adjusted":4788.9502,"daily_return":-0.004774,"cum_return":0.056019},{"date":"2021-08-27","open":4806.8999,"high":4891.2002,"low":4806.8999,"close":4814.4199,"volume":0,"adjusted":4814.4199,"daily_return":0.005318,"cum_return":0.061635},{"date":"2021-09-03","open":4764.8599,"high":4852.8501,"low":4764.8599,"close":4803.54,"volume":0,"adjusted":4803.54,"daily_return":-0.00226,"cum_return":0.059236},{"date":"2021-09-10","open":4832.2598,"high":4853.1802,"low":4697.7002,"close":4737.5698,"volume":0,"adjusted":4737.5698,"daily_return":-0.013734,"cum_return":0.044689},{"date":"2021-09-17","open":4707.4199,"high":4834.6802,"low":4707.4199,"close":4834.6802,"volume":0,"adjusted":4834.6802,"daily_return":0.020498,"cum_return":0.066103},{"date":"2021-09-23","open":4850.98,"high":4879.6099,"low":4757.6099,"close":4757.6099,"volume":0,"adjusted":4757.6099,"daily_return":-0.015941,"cum_return":0.049108},{"date":"2021-10-01","open":4871.3301,"high":4887.48,"low":4764.7402,"close":4764.7402,"volume":0,"adjusted":4764.7402,"daily_return":0.001499,"cum_return":0.05068},{"date":"2021-10-08","open":4774.8198,"high":4807.9702,"low":4748.23,"close":4807.9702,"volume":0,"adjusted":4807.9702,"daily_return":0.009073,"cum_return":0.060213},{"date":"2021-10-15","open":4853.7998,"high":4853.7998,"low":4787.8701,"close":4813.1401,"volume":0,"adjusted":4813.1401,"daily_return":0.001075,"cum_return":0.061353},{"date":"2021-10-22","open":4836.2998,"high":4896.02,"low":4824.0698,"close":4896.02,"volume":0,"adjusted":4896.02,"daily_return":0.01722,"cum_return":0.079629},{"date":"2021-10-29","open":4905.0098,"high":4976.0498,"low":4905.0098,"close":4939.3198,"volume":0,"adjusted":4939.3198,"daily_return":0.008844,"cum_return":0.089177},{"date":"2021-11-05","open":5006.2402,"high":5009.7998,"low":4907.9102,"close":4907.9102,"volume":0,"adjusted":4907.9102,"daily_return":-0.006359,"cum_return":0.082251},{"date":"2021-11-12","open":4874.0801,"high":5041.7002,"low":4874.0801,"close":5041.7002,"volume":0,"adjusted":5041.7002,"daily_return":0.02726,"cum_return":0.111753},{"date":"2021-11-19","open":5025.9199,"high":5150.98,"low":5025.9199,"close":5119.4399,"volume":0,"adjusted":5119.4399,"daily_return":0.015419,"cum_return":0.128896},{"date":"2021-11-26","open":5111.6001,"high":5117.9199,"low":5095.5098,"close":5095.5098,"volume":0,"adjusted":5095.5098,"daily_return":-0.004674,"cum_return":0.123619},{"date":"2021-12-03","open":5074.7798,"high":5074.7798,"low":4982.98,"close":5061.9199,"volume":0,"adjusted":5061.9199,"daily_return":-0.006592,"cum_return":0.116212},{"date":"2021-12-10","open":4991.3999,"high":5107.1699,"low":4991.3999,"close":5076.5698,"volume":0,"adjusted":5076.5698,"daily_return":0.002894,"cum_return":0.119442},{"date":"2021-12-17","open":5049.4399,"high":5049.4399,"low":4938.1802,"close":4938.1802,"volume":0,"adjusted":4938.1802,"daily_return":-0.02726,"cum_return":0.088926},{"date":"2021-12-24","open":4804.7002,"high":4906.29,"low":4804.7002,"close":4851.5,"volume":0,"adjusted":4851.5,"daily_return":-0.017553,"cum_return":0.069812},{"date":"2021-12-31","open":4929.4399,"high":5008.25,"low":4929.4399,"close":4999.21,"volume":0,"adjusted":4999.21,"daily_return":0.030446,"cum_return":0.102383},{"date":"2022-01-07","open":4979.79,"high":5058.6499,"low":4893.1602,"close":4903.1602,"volume":0,"adjusted":4903.1602,"daily_return":-0.019213,"cum_return":0.081203},{"date":"2022-01-14","open":4958.0498,"high":5000.3701,"low":4958.0498,"close":4969.0098,"volume":0,"adjusted":4969.0098,"daily_return":0.01343,"cum_return":0.095724},{"date":"2022-01-21","open":4967.6899,"high":null,"low":null,"close":4829.71,"volume":null,"adjusted":4829.71,"daily_return":-0.028034,"cum_return":0.065007},{"date":"2022-01-28","open":4807.25,"high":4807.25,"low":4711.6401,"close":4786.3599,"volume":0,"adjusted":4786.3599,"daily_return":-0.008976,"cum_return":0.055448},{"date":"2022-02-04","open":4793.9102,"high":4858.6299,"low":4726.71,"close":4858.6299,"volume":0,"adjusted":4858.6299,"daily_return":0.015099,"cum_return":0.071384},{"date":"2022-02-11","open":4846.7402,"high":4848,"low":4796.5698,"close":4796.5698,"volume":0,"adjusted":4796.5698,"daily_return":-0.012773,"cum_return":0.057699},{"date":"2022-02-18","open":4726.6099,"high":4813.6299,"low":4726.6099,"close":4779.71,"volume":0,"adjusted":4779.71,"daily_return":-0.003515,"cum_return":0.053981},{"date":"2022-02-25","open":4716.9102,"high":4716.9102,"low":4564.23,"close":4564.23,"volume":0,"adjusted":4564.23,"daily_return":-0.045082,"cum_return":0.006465},{"date":"2022-03-04","open":4588.5698,"high":4588.5698,"low":4445.3398,"close":4445.3398,"volume":0,"adjusted":4445.3398,"daily_return":-0.026048,"cum_return":-0.019751},{"date":"2022-03-11","open":4263.6299,"high":4263.6299,"low":4158.8901,"close":4158.8901,"volume":0,"adjusted":4158.8901,"daily_return":-0.064438,"cum_return":-0.082917},{"date":"2022-03-18","open":4067.72,"high":4322.7998,"low":3974.45,"close":4322.7998,"volume":0,"adjusted":4322.7998,"daily_return":0.039412,"cum_return":-0.046773},{"date":"2022-03-25","open":4309.73,"high":4325.4502,"low":4218.8198,"close":4218.8198,"volume":0,"adjusted":4218.8198,"daily_return":-0.024054,"cum_return":-0.069702},{"date":"2022-04-01","open":4253.23,"high":4318.5801,"low":4249.2598,"close":4318.5801,"volume":0,"adjusted":4318.5801,"daily_return":0.023646,"cum_return":-0.047703},{"date":"2022-04-08","open":4361.1699,"high":4361.1699,"low":4248.0698,"close":4248.0698,"volume":0,"adjusted":4248.0698,"daily_return":-0.016327,"cum_return":-0.063252},{"date":"2022-04-14","open":4173.8999,"high":4207.7402,"low":4134.8101,"close":4207.7402,"volume":0,"adjusted":4207.7402,"daily_return":-0.009494,"cum_return":-0.072145},{"date":"2022-04-22","open":4203.4502,"high":4312.5098,"low":4203.4502,"close":4312.5098,"volume":0,"adjusted":4312.5098,"daily_return":0.024899,"cum_return":-0.049042},{"date":"2022-04-29","open":4231.8799,"high":4366.3999,"low":4231.8799,"close":4366.3999,"volume":0,"adjusted":4366.3999,"daily_return":0.012496,"cum_return":-0.037158},{"date":"2022-05-06","open":4333.54,"high":4333.54,"low":4198.4902,"close":4198.4902,"volume":0,"adjusted":4198.4902,"daily_return":-0.038455,"cum_return":-0.074184},{"date":"2022-05-13","open":4210.3599,"high":4210.3599,"low":4074.3501,"close":4168.3101,"volume":0,"adjusted":4168.3101,"daily_return":-0.007188,"cum_return":-0.08084},{"date":"2022-05-20","open":4190.4302,"high":4238.1699,"low":4118.3599,"close":4210.5498,"volume":0,"adjusted":4210.5498,"daily_return":0.010134,"cum_return":-0.071525},{"date":"2022-05-27","open":4154.3398,"high":4157.96,"low":4092.4199,"close":4157.96,"volume":0,"adjusted":4157.96,"daily_return":-0.01249,"cum_return":-0.083122},{"date":"2022-06-03","open":4227.2998,"high":4308.8901,"low":4227.2998,"close":4242.79,"volume":0,"adjusted":4242.79,"daily_return":0.020402,"cum_return":-0.064416},{"date":"2022-06-10","open":4214.2002,"high":4268.7598,"low":4166.4302,"close":4268.7598,"volume":0,"adjusted":4268.7598,"daily_return":0.006121,"cum_return":-0.058689},{"date":"2022-06-17","open":4198.3301,"high":4198.3301,"low":4123.2598,"close":4123.2598,"volume":0,"adjusted":4123.2598,"daily_return":-0.034085,"cum_return":-0.090774},{"date":"2022-06-24","open":4121.1802,"high":4139.8999,"low":4057.22,"close":4124.54,"volume":0,"adjusted":4124.54,"daily_return":0.000311,"cum_return":-0.090491},{"date":"2022-07-01","open":4193.3398,"high":4249.79,"low":4193.3398,"close":4204.8599,"volume":0,"adjusted":4204.8599,"daily_return":0.019474,"cum_return":-0.07278},{"date":"2022-07-08","open":4175.1401,"high":4340.4702,"low":4175.1401,"close":4340.4702,"volume":0,"adjusted":4340.4702,"daily_return":0.032251,"cum_return":-0.042876},{"date":"2022-07-15","open":4314.6699,"high":4314.6699,"low":4226.0801,"close":4245.3301,"volume":0,"adjusted":4245.3301,"daily_return":-0.021919,"cum_return":-0.063856},{"date":"2022-07-22","open":4321.1099,"high":4370.4502,"low":4309.6099,"close":4309.6099,"volume":0,"adjusted":4309.6099,"daily_return":0.015141,"cum_return":-0.049681},{"date":"2022-07-29","open":4287.9302,"high":4320.71,"low":4265.1001,"close":4265.1001,"volume":0,"adjusted":4265.1001,"daily_return":-0.010328,"cum_return":-0.059496},{"date":"2022-08-05","open":4216.46,"high":4342.77,"low":4215.1602,"close":4342.77,"volume":0,"adjusted":4342.77,"daily_return":0.018211,"cum_return":-0.042369},{"date":"2022-08-12","open":4286.3701,"high":4286.3701,"low":4153.46,"close":4265.5698,"volume":0,"adjusted":4265.5698,"daily_return":-0.017777,"cum_return":-0.059393},{"date":"2022-08-19","open":4309.21,"high":4401.4399,"low":4309.21,"close":4401.4399,"volume":0,"adjusted":4401.4399,"daily_return":0.031853,"cum_return":-0.029432},{"date":"2022-08-26","open":4350.96,"high":4354.2998,"low":4300.27,"close":4354.2998,"volume":0,"adjusted":4354.2998,"daily_return":-0.01071,"cum_return":-0.039827},{"date":"2022-09-02","open":4362.9702,"high":4362.9702,"low":4290.0698,"close":4290.0698,"volume":0,"adjusted":4290.0698,"daily_return":-0.014751,"cum_return":-0.05399},{"date":"2022-09-09","open":4264.8901,"high":4293.1499,"low":4248.6802,"close":4293.1499,"volume":0,"adjusted":4293.1499,"daily_return":0.000718,"cum_return":-0.053311},{"date":"2022-09-16","open":4286.3999,"high":4358.5898,"low":4262.2002,"close":4262.2002,"volume":0,"adjusted":4262.2002,"daily_return":-0.007209,"cum_return":-0.060136},{"date":"2022-09-23","open":4278.6001,"high":4290.77,"low":4157.9702,"close":4157.9702,"volume":0,"adjusted":4157.9702,"daily_return":-0.024455,"cum_return":-0.08312},{"date":"2022-09-30","open":4118.8901,"high":4118.8901,"low":4032.9199,"close":4034.1299,"volume":0,"adjusted":4034.1299,"daily_return":-0.029784,"cum_return":-0.110428},{"date":"2022-10-07","open":4007.21,"high":4167.4199,"low":4007.21,"close":4146.1499,"volume":0,"adjusted":4146.1499,"daily_return":0.027768,"cum_return":-0.085726},{"date":"2022-10-14","open":4103.4702,"high":4103.4702,"low":4006.21,"close":4030.1699,"volume":0,"adjusted":4030.1699,"daily_return":-0.027973,"cum_return":-0.111301},{"date":"2022-10-21","open":4007.3899,"high":4083.25,"low":4007.3899,"close":4043.46,"volume":0,"adjusted":4043.46,"daily_return":0.003298,"cum_return":-0.10837},{"date":"2022-10-28","open":3987.05,"high":3987.05,"low":3931.04,"close":3943.6101,"volume":0,"adjusted":3943.6101,"daily_return":-0.024694,"cum_return":-0.130388},{"date":"2022-11-04","open":4018.8899,"high":4099.21,"low":4018.8899,"close":4091.47,"volume":0,"adjusted":4091.47,"daily_return":0.037494,"cum_return":-0.097784},{"date":"2022-11-11","open":4082.77,"high":4157.23,"low":3993.01,"close":4157.23,"volume":0,"adjusted":4157.23,"daily_return":0.016072,"cum_return":-0.083283},{"date":"2022-11-18","open":4178.6401,"high":4268.3999,"low":4178.6401,"close":4185.0098,"volume":0,"adjusted":4185.0098,"daily_return":0.006682,"cum_return":-0.077157},{"date":"2022-11-25","open":4159.3398,"high":4159.3398,"low":4087.05,"close":4152.6602,"volume":0,"adjusted":4152.6602,"daily_return":-0.00773,"cum_return":-0.084291},{"date":"2022-12-02","open":4105.7598,"high":4433.96,"low":4105.7598,"close":4397.96,"volume":0,"adjusted":4397.96,"daily_return":0.059071,"cum_return":-0.030199},{"date":"2022-12-09","open":4397.6499,"high":4397.6499,"low":4247.5,"close":4380.46,"volume":0,"adjusted":4380.46,"daily_return":-0.003979,"cum_return":-0.034058},{"date":"2022-12-15","open":4371.04,"high":4371.04,"low":4280.8901,"close":4305.8901,"volume":0,"adjusted":4305.8901,"daily_return":-0.017023,"cum_return":-0.050502},{"date":"2022-12-23","open":4269.0698,"high":4269.0698,"low":4176.4502,"close":4176.4502,"volume":0,"adjusted":4176.4502,"daily_return":-0.030061,"cum_return":-0.079045},{"date":"2022-12-30","open":4231.3799,"high":4231.3799,"low":4162.8799,"close":4188.1401,"volume":0,"adjusted":4188.1401,"daily_return":0.002799,"cum_return":-0.076467},{"date":"2023-01-06","open":4203.4399,"high":4376.5,"low":4203.4399,"close":4376.5,"volume":0,"adjusted":4376.5,"daily_return":0.044975,"cum_return":-0.034931},{"date":"2023-01-13","open":4426.5698,"high":4460.0298,"low":4419.0898,"close":4459.0498,"volume":0,"adjusted":4459.0498,"daily_return":0.018862,"cum_return":-0.016728},{"date":"2023-01-20","open":4515.0898,"high":4605.7202,"low":4513.7202,"close":4584.8999,"volume":0,"adjusted":4584.8999,"daily_return":0.028224,"cum_return":0.011023},{"date":"2023-01-27","open":4601.7002,"high":4680.7798,"low":4601.7002,"close":4677.73,"volume":0,"adjusted":4677.73,"daily_return":0.020247,"cum_return":0.031493},{"date":"2023-02-03","open":4679.29,"high":4683.9902,"low":4607.2402,"close":4683.9902,"volume":0,"adjusted":4683.9902,"daily_return":0.001338,"cum_return":0.032874},{"date":"2023-02-10","open":4631.1299,"high":4692.6499,"low":4618.8101,"close":4692.6499,"volume":0,"adjusted":4692.6499,"daily_return":0.001849,"cum_return":0.034783},{"date":"2023-02-17","open":4666.1699,"high":4724.2202,"low":4640.8799,"close":4640.8799,"volume":0,"adjusted":4640.8799,"daily_return":-0.011032,"cum_return":0.023368},{"date":"2023-02-24","open":4685.0801,"high":4685.0801,"low":4588.52,"close":4610.2798,"volume":0,"adjusted":4610.2798,"daily_return":-0.006594,"cum_return":0.01662},{"date":"2023-03-03","open":4575.0298,"high":4599.8398,"low":4546.73,"close":4599.8398,"volume":0,"adjusted":4599.8398,"daily_return":-0.002264,"cum_return":0.014318},{"date":"2023-03-10","open":4646.5801,"high":4693.7998,"low":4455.0801,"close":4455.0801,"volume":0,"adjusted":4455.0801,"daily_return":-0.031471,"cum_return":-0.017603},{"date":"2023-03-17","open":4477.3701,"high":4497.7402,"low":4399.8999,"close":4497.7402,"volume":0,"adjusted":4497.7402,"daily_return":0.009576,"cum_return":-0.008196},{"date":"2023-03-24","open":4479.73,"high":4540.77,"low":4479.73,"close":4540.77,"volume":0,"adjusted":4540.77,"daily_return":0.009567,"cum_return":0.001292},{"date":"2023-03-31","open":4542.3999,"high":4571.7402,"low":4529.1001,"close":4529.1001,"volume":0,"adjusted":4529.1001,"daily_return":-0.00257,"cum_return":-0.001281},{"date":"2023-04-06","open":4533.77,"high":4620.48,"low":4533.77,"close":4620.48,"volume":0,"adjusted":4620.48,"daily_return":0.020176,"cum_return":0.018869},{"date":"2023-04-14","open":4706.25,"high":4706.25,"low":4636.96,"close":4667.9199,"volume":0,"adjusted":4667.9199,"daily_return":0.010267,"cum_return":0.02933},{"date":"2023-04-21","open":4727.7598,"high":4727.7598,"low":4564.6401,"close":4564.6401,"volume":0,"adjusted":4564.6401,"daily_return":-0.022125,"cum_return":0.006556},{"date":"2023-04-28","open":4562.1299,"high":4592.9702,"low":4562.1299,"close":4592.9702,"volume":0,"adjusted":4592.9702,"daily_return":0.006206,"cum_return":0.012803},{"date":"2023-05-05","open":4633.21,"high":4654.7202,"low":4559.6099,"close":4654.7202,"volume":0,"adjusted":4654.7202,"daily_return":0.013444,"cum_return":0.026419},{"date":"2023-05-12","open":4624.6201,"high":4853.6099,"low":4624.6201,"close":4853.6099,"volume":0,"adjusted":4853.6099,"daily_return":0.042729,"cum_return":0.070277},{"date":"2023-05-19","open":4807.1401,"high":4927.8198,"low":4807.1401,"close":4927.8198,"volume":0,"adjusted":4927.8198,"daily_return":0.01529,"cum_return":0.086641},{"date":"2023-05-26","open":4897.5498,"high":4925.7002,"low":4819.6299,"close":4925.7002,"volume":0,"adjusted":4925.7002,"daily_return":-0.00043,"cum_return":0.086174},{"date":"2023-06-02","open":4937.8701,"high":4976.6099,"low":4888.8799,"close":4976.6099,"volume":0,"adjusted":4976.6099,"daily_return":0.010336,"cum_return":0.0974},{"date":"2023-06-09","open":4927.2202,"high":null,"low":null,"close":4859.0801,"volume":null,"adjusted":4859.0801,"daily_return":-0.023616,"cum_return":0.071483},{"date":"2023-06-15","open":4830.9102,"high":4912.5298,"low":4820.3198,"close":4912.5298,"volume":0,"adjusted":4912.5298,"daily_return":0.011,"cum_return":0.083269},{"date":"2023-06-23","open":4837.54,"high":4839.71,"low":4794.29,"close":4833.5601,"volume":0,"adjusted":4833.5601,"daily_return":-0.016075,"cum_return":0.065856},{"date":"2023-06-30","open":4794.6699,"high":4869.3901,"low":4780.6299,"close":4869.3901,"volume":0,"adjusted":4869.3901,"daily_return":0.007413,"cum_return":0.073757},{"date":"2023-07-07","open":4906.7798,"high":4909.52,"low":4832.7002,"close":4832.7002,"volume":0,"adjusted":4832.7002,"daily_return":-0.007535,"cum_return":0.065666},{"date":"2023-07-14","open":4831.1699,"high":4857.7402,"low":4774.0298,"close":4857.7402,"volume":0,"adjusted":4857.7402,"daily_return":0.005181,"cum_return":0.071188},{"date":"2023-07-21","open":4857.04,"high":4857.04,"low":4754.0801,"close":4754.0801,"volume":0,"adjusted":4754.0801,"daily_return":-0.021339,"cum_return":0.048329},{"date":"2023-07-28","open":4691.0898,"high":4807.1699,"low":4691.0898,"close":4807.1699,"volume":0,"adjusted":4807.1699,"daily_return":0.011167,"cum_return":0.060036},{"date":"2023-08-04","open":4867.8901,"high":4977.8101,"low":4867.8901,"close":4908.6802,"volume":0,"adjusted":4908.6802,"daily_return":0.021116,"cum_return":0.082421},{"date":"2023-08-11","open":4980.2402,"high":4985.8398,"low":4920.5,"close":4920.5,"volume":0,"adjusted":4920.5,"daily_return":0.002408,"cum_return":0.085027},{"date":"2023-08-18","open":4912.7002,"high":4912.7002,"low":4771.52,"close":4771.52,"volume":0,"adjusted":4771.52,"daily_return":-0.030277,"cum_return":0.052175},{"date":"2023-08-25","open":4763.1602,"high":4797.1699,"low":4684.0698,"close":4737.8799,"volume":0,"adjusted":4737.8799,"daily_return":-0.00705,"cum_return":0.044757},{"date":"2023-09-01","open":4714.6602,"high":4838.52,"low":4714.6602,"close":4824.7998,"volume":0,"adjusted":4824.7998,"daily_return":0.018346,"cum_return":0.063924},{"date":"2023-09-08","open":4936.98,"high":4940.1499,"low":4831.4102,"close":4831.4102,"volume":0,"adjusted":4831.4102,"daily_return":0.00137,"cum_return":0.065382},{"date":"2023-09-15","open":4802.6099,"high":4904.8901,"low":4771.8501,"close":4904.8901,"volume":0,"adjusted":4904.8901,"daily_return":0.015209,"cum_return":0.081585},{"date":"2023-09-22","open":4836.6299,"high":4836.6299,"low":4704.6099,"close":4710.1201,"volume":0,"adjusted":4710.1201,"daily_return":-0.039709,"cum_return":0.038636},{"date":"2023-09-29","open":4694.8799,"high":4727.3501,"low":4663.77,"close":4663.77,"volume":0,"adjusted":4663.77,"daily_return":-0.009841,"cum_return":0.028415},{"date":"2023-10-06","open":4750.1201,"high":4750.1201,"low":4682.7798,"close":4733.48,"volume":0,"adjusted":4733.48,"daily_return":0.014947,"cum_return":0.043787},{"date":"2023-10-13","open":4734.3101,"high":4754.1899,"low":4687.1299,"close":4711.0898,"volume":0,"adjusted":4711.0898,"daily_return":-0.00473,"cum_return":0.03885},{"date":"2023-10-20","open":4635.5898,"high":4681.1099,"low":4578.6099,"close":4578.6099,"volume":0,"adjusted":4578.6099,"daily_return":-0.028121,"cum_return":0.009636},{"date":"2023-10-27","open":4534.3701,"high":4585.9302,"low":4511.9102,"close":4518.8901,"volume":0,"adjusted":4518.8901,"daily_return":-0.013043,"cum_return":-0.003533},{"date":"2023-11-03","open":4529.3398,"high":4532.4399,"low":4467.3398,"close":4532.4399,"volume":0,"adjusted":4532.4399,"daily_return":0.002998,"cum_return":-0.000545},{"date":"2023-11-10","open":4643.3101,"high":4652.71,"low":4624.0298,"close":4652.71,"volume":0,"adjusted":4652.71,"daily_return":0.026535,"cum_return":0.025976},{"date":"2023-11-17","open":4667.5801,"high":4711.6401,"low":4615.8198,"close":4693.6602,"volume":0,"adjusted":4693.6602,"daily_return":0.008801,"cum_return":0.035006},{"date":"2023-11-24","open":4741.4302,"high":4859.1899,"low":4741.4302,"close":4828.98,"volume":0,"adjusted":4828.98,"daily_return":0.02883,"cum_return":0.064846},{"date":"2023-12-01","open":4782.3101,"high":4877.9502,"low":4772.3301,"close":4778.3101,"volume":0,"adjusted":4778.3101,"daily_return":-0.010493,"cum_return":0.053672},{"date":"2023-12-08","open":4808.73,"high":4808.73,"low":4756.3701,"close":4804.8599,"volume":0,"adjusted":4804.8599,"daily_return":0.005556,"cum_return":0.059527},{"date":"2023-12-14","open":4840.8799,"high":4840.8799,"low":4737.1201,"close":4737.1201,"volume":0,"adjusted":4737.1201,"daily_return":-0.014098,"cum_return":0.04459},{"date":"2023-12-22","open":4834.6201,"high":4834.6201,"low":4737.0298,"close":4772.1802,"volume":0,"adjusted":4772.1802,"daily_return":0.007401,"cum_return":0.052321},{"date":"2023-12-29","open":4824.0498,"high":4918.6699,"low":4824.0498,"close":4878.5298,"volume":0,"adjusted":4878.5298,"daily_return":0.022285,"cum_return":0.075772},{"date":"2024-01-05","open":4910.8101,"high":4910.8101,"low":4839.3198,"close":4839.3198,"volume":0,"adjusted":4839.3198,"daily_return":-0.008037,"cum_return":0.067126},{"date":"2024-01-12","open":4817.0801,"high":4825.7798,"low":4795.1201,"close":4806.4502,"volume":0,"adjusted":4806.4502,"daily_return":-0.006792,"cum_return":0.059878},{"date":"2024-01-19","open":4830.3198,"high":4830.3198,"low":4728.9702,"close":4799.9702,"volume":0,"adjusted":4799.9702,"daily_return":-0.001348,"cum_return":0.058449},{"date":"2024-01-26","open":4803.9902,"high":4839.46,"low":4782.8301,"close":4782.8301,"volume":0,"adjusted":4782.8301,"daily_return":-0.003571,"cum_return":0.054669},{"date":"2024-02-02","open":4825.0698,"high":4838.75,"low":4695.6401,"close":4838.75,"volume":0,"adjusted":4838.75,"daily_return":0.011692,"cum_return":0.067},{"date":"2024-02-09","open":4851.5498,"high":4901.7998,"low":4851.5498,"close":4901.23,"volume":0,"adjusted":4901.23,"daily_return":0.012912,"cum_return":0.080778},{"date":"2024-02-16","open":4900,"high":5002,"low":4897,"close":4954.75,"volume":4227,"adjusted":4954.75,"daily_return":0.01092,"cum_return":0.09258},{"date":"2024-02-23","open":4988.04,"high":5120.0898,"low":4979.5098,"close":5120.0898,"volume":0,"adjusted":5120.0898,"daily_return":0.03337,"cum_return":0.129039},{"date":"2024-03-01","open":5135,"high":5171,"low":4950,"close":5089,"volume":12329,"adjusted":5089,"daily_return":-0.006072,"cum_return":0.122183},{"date":"2024-03-08","open":5134,"high":5134,"low":4972,"close":5025,"volume":2159,"adjusted":5025,"daily_return":-0.012576,"cum_return":0.10807},{"date":"2024-03-15","open":4989,"high":5200,"low":4977,"close":5035,"volume":6046,"adjusted":5035,"daily_return":0.00199,"cum_return":0.110276},{"date":"2024-03-22","open":5085,"high":5158,"low":4998,"close":5102,"volume":6130,"adjusted":5102,"daily_return":0.013307,"cum_return":0.12505},{"date":"2024-03-28","open":5102,"high":5163,"low":5057,"close":5122,"volume":3590,"adjusted":5122,"daily_return":0.00392,"cum_return":0.12946},{"date":"2024-04-05","open":5080,"high":5147,"low":5009,"close":5044,"volume":3946,"adjusted":5044,"daily_return":-0.015228,"cum_return":0.11226},{"date":"2024-04-12","open":5104,"high":5105,"low":4997,"close":5040,"volume":7158,"adjusted":5040,"daily_return":-0.000793,"cum_return":0.111378},{"date":"2024-04-19","open":5079,"high":5079,"low":4880,"close":4997,"volume":2997,"adjusted":4997,"daily_return":-0.008532,"cum_return":0.101896},{"date":"2024-04-26","open":4950,"high":5128,"low":4921,"close":5028,"volume":16626,"adjusted":5028,"daily_return":0.006204,"cum_return":0.108732},{"date":"2024-05-03","open":5014,"high":5132,"low":4975,"close":5096,"volume":20245,"adjusted":5096,"daily_return":0.013524,"cum_return":0.123727},{"date":"2024-05-10","open":5069,"high":5185,"low":5000,"close":5140,"volume":1623,"adjusted":5140,"daily_return":0.008634,"cum_return":0.133429},{"date":"2024-05-17","open":5174,"high":5220,"low":5066,"close":5184,"volume":27852,"adjusted":5184,"daily_return":0.00856,"cum_return":0.143132},{"date":"2024-05-24","open":5200,"high":5266,"low":5084,"close":5177,"volume":14300,"adjusted":5177,"daily_return":-0.00135,"cum_return":0.141588},{"date":"2024-05-31","open":5239,"high":5239,"low":5057,"close":5083,"volume":7899,"adjusted":5083,"daily_return":-0.018157,"cum_return":0.12086},{"date":"2024-06-07","open":5218,"high":5306,"low":5030,"close":5220,"volume":3523,"adjusted":5220,"daily_return":0.026953,"cum_return":0.15107},{"date":"2024-06-14","open":5129,"high":5215,"low":5049,"close":5120,"volume":2673,"adjusted":5120,"daily_return":-0.019157,"cum_return":0.129019},{"date":"2024-06-21","open":5140,"high":5221,"low":4998,"close":5034,"volume":18833,"adjusted":5034,"daily_return":-0.016797,"cum_return":0.110055},{"date":"2024-06-28","open":5034,"high":5205,"low":5034,"close":5178,"volume":3086,"adjusted":5178,"daily_return":0.028605,"cum_return":0.141809},{"date":"2024-07-05","open":5147,"high":5300,"low":5119,"close":5277,"volume":5842,"adjusted":5277,"daily_return":0.019119,"cum_return":0.163639},{"date":"2024-07-12","open":5300,"high":5357,"low":5199,"close":5311,"volume":7550,"adjusted":5311,"daily_return":0.006443,"cum_return":0.171137},{"date":"2024-07-19","open":5269,"high":5450,"low":5176,"close":5199,"volume":11289,"adjusted":5199,"daily_return":-0.021088,"cum_return":0.146439},{"date":"2024-07-26","open":5254,"high":5277,"low":5100,"close":5135,"volume":2794,"adjusted":5135,"daily_return":-0.01231,"cum_return":0.132327},{"date":"2024-08-02","open":5224,"high":5350,"low":4980,"close":5025,"volume":12902,"adjusted":5025,"daily_return":-0.021422,"cum_return":0.10807},{"date":"2024-08-08","open":4997,"high":5132,"low":4822,"close":5101,"volume":11226,"adjusted":5101,"daily_return":0.015124,"cum_return":0.124829},{"date":"2024-08-16","open":5150,"high":5213,"low":5060,"close":5163,"volume":6842,"adjusted":5163,"daily_return":0.012154,"cum_return":0.138501},{"date":"2024-08-23","open":5129,"high":5265,"low":5129,"close":5186,"volume":95870,"adjusted":5186,"daily_return":0.004455,"cum_return":0.143573},{"date":"2024-08-30","open":5131,"high":5223,"low":5081,"close":5148,"volume":311536,"adjusted":5148,"daily_return":-0.007327,"cum_return":0.135193},{"date":"2024-09-06","open":5130,"high":5212,"low":4998,"close":5017,"volume":19875,"adjusted":5017,"daily_return":-0.025447,"cum_return":0.106306},{"date":"2024-09-13","open":5097,"high":5108,"low":5004,"close":5107,"volume":1349,"adjusted":5107,"daily_return":0.017939,"cum_return":0.126152},{"date":"2024-09-20","open":5142,"high":5158,"low":5056,"close":5118,"volume":9188,"adjusted":5118,"daily_return":0.002154,"cum_return":0.128578},{"date":"2024-09-27","open":5061,"high":5400,"low":5061,"close":5367,"volume":5032,"adjusted":5367,"daily_return":0.048652,"cum_return":0.183485},{"date":"2024-10-04","open":5396,"high":5520,"low":5230,"close":5444,"volume":2744,"adjusted":5444,"daily_return":0.014347,"cum_return":0.200465},{"date":"2024-10-11","open":5524,"high":5542,"low":5291,"close":5353,"volume":20399,"adjusted":5353,"daily_return":-0.016716,"cum_return":0.180398},{"date":"2024-10-18","open":5327,"high":5441,"low":5314,"close":5387,"volume":17719,"adjusted":5387,"daily_return":0.006352,"cum_return":0.187896},{"date":"2024-10-25","open":5304,"high":5369,"low":5252,"close":5308,"volume":15576,"adjusted":5308,"daily_return":-0.014665,"cum_return":0.170475},{"date":"2024-11-01","open":5361,"high":5398,"low":5070,"close":5202,"volume":8710,"adjusted":5202,"daily_return":-0.01997,"cum_return":0.147101},{"date":"2024-11-08","open":5276,"high":5312,"low":4979,"close":5214,"volume":3303,"adjusted":5214,"daily_return":0.002307,"cum_return":0.149747},{"date":"2024-11-15","open":4956,"high":5500,"low":4956,"close":5198,"volume":14145,"adjusted":5198,"daily_return":-0.003069,"cum_return":0.146219},{"date":"2024-11-22","open":5250,"high":5270,"low":4980,"close":5215,"volume":14798,"adjusted":5215,"daily_return":0.00327,"cum_return":0.149968},{"date":"2024-11-29","open":5275,"high":5379,"low":5116,"close":5147,"volume":18303,"adjusted":5147,"daily_return":-0.013039,"cum_return":0.134973},{"date":"2024-12-06","open":4950,"high":5327,"low":4950,"close":5271,"volume":18349,"adjusted":5271,"daily_return":0.024092,"cum_return":0.162316},{"date":"2024-12-13","open":5336,"high":5398,"low":5121,"close":5239,"volume":14232,"adjusted":5239,"daily_return":-0.006071,"cum_return":0.15526},{"date":"2024-12-20","open":5040,"high":5305,"low":5040,"close":5216,"volume":2964,"adjusted":5216,"daily_return":-0.00439,"cum_return":0.150188},{"date":"2024-12-27","open":5216,"high":5438,"low":5216,"close":5377,"volume":40615,"adjusted":5377,"daily_return":0.030867,"cum_return":0.185691},{"date":"2025-01-03","open":5390,"high":5550,"low":5340,"close":5350,"volume":10654,"adjusted":5350,"daily_return":-0.005021,"cum_return":0.179737},{"date":"2025-01-09","open":5404,"high":5404,"low":5327,"close":5362,"volume":3350,"adjusted":5362,"daily_return":0.002243,"cum_return":0.182383},{"date":"2025-01-17","open":5271,"high":5384,"low":5270,"close":5347,"volume":14749,"adjusted":5347,"daily_return":-0.002797,"cum_return":0.179075},{"date":"2025-01-24","open":5350,"high":5350,"low":5310,"close":5316,"volume":15432,"adjusted":5316,"daily_return":-0.005798,"cum_return":0.172239},{"date":"2025-01-31","open":5319,"high":5456,"low":5307,"close":5421,"volume":8465,"adjusted":5421,"daily_return":0.019752,"cum_return":0.195393},{"date":"2025-02-07","open":5354,"high":5618,"low":5354,"close":5444,"volume":5657,"adjusted":5444,"daily_return":0.004243,"cum_return":0.200465},{"date":"2025-02-14","open":5443,"high":5540,"low":5419,"close":5505,"volume":16985,"adjusted":5505,"daily_return":0.011205,"cum_return":0.213916},{"date":"2025-02-21","open":5560,"high":5646,"low":5536,"close":5619,"volume":4411,"adjusted":5619,"daily_return":0.020708,"cum_return":0.239054},{"date":"2025-02-28","open":5570,"high":5618,"low":5374,"close":5394,"volume":36824,"adjusted":5394,"daily_return":-0.040043,"cum_return":0.189439},{"date":"2025-03-07","open":5410,"high":5600,"low":5378,"close":5488,"volume":28695,"adjusted":5488,"daily_return":0.017427,"cum_return":0.210167},{"date":"2025-03-14","open":5473,"high":5480,"low":5377,"close":5446,"volume":33118,"adjusted":5446,"daily_return":-0.007653,"cum_return":0.200906},{"date":"2025-03-20","open":5497,"high":5570,"low":5450,"close":5508,"volume":4809,"adjusted":5508,"daily_return":0.011385,"cum_return":0.214578},{"date":"2025-03-28","open":5528,"high":5531,"low":5400,"close":5437,"volume":5707,"adjusted":5437,"daily_return":-0.01289,"cum_return":0.198921},{"date":"2025-04-04","open":5396,"high":5554,"low":5332,"close":5229,"volume":3869,"adjusted":5229,"daily_return":-0.038256,"cum_return":0.153055},{"date":"2025-04-11","open":5043,"high":5451,"low":5043,"close":5370,"volume":20087,"adjusted":5370,"daily_return":0.026965,"cum_return":0.184147},{"date":"2025-04-17","open":5380,"high":5439,"low":5364,"close":5375,"volume":3606,"adjusted":5375,"daily_return":0.000931,"cum_return":0.18525},{"date":"2025-04-25","open":5381,"high":5569,"low":5340,"close":5515,"volume":5975,"adjusted":5515,"daily_return":0.026047,"cum_return":0.216121},{"date":"2025-05-02","open":5549,"high":5679,"low":5487,"close":5646,"volume":17535,"adjusted":5646,"daily_return":0.023753,"cum_return":0.245008},{"date":"2025-05-09","open":5686,"high":5717,"low":5530,"close":5607,"volume":11490,"adjusted":5607,"daily_return":-0.006908,"cum_return":0.236408},{"date":"2025-05-16","open":5732,"high":5826,"low":5660,"close":5713,"volume":7806,"adjusted":5713,"daily_return":0.018905,"cum_return":0.259782},{"date":"2025-05-23","open":5689,"high":5697,"low":5616,"close":5643,"volume":4940,"adjusted":5643,"daily_return":-0.012253,"cum_return":0.244347},{"date":"2025-05-30","open":5664,"high":5670,"low":5549,"close":5629,"volume":4491,"adjusted":5629,"daily_return":-0.002481,"cum_return":0.241259},{"date":"2025-06-06","open":5611,"high":5736,"low":5604,"close":5714,"volume":45805,"adjusted":5714,"daily_return":0.0151,"cum_return":0.260003},{"date":"2025-06-13","open":5772,"high":5871,"low":5725,"close":5780,"volume":20568,"adjusted":5780,"daily_return":0.011551,"cum_return":0.274557},{"date":"2025-06-20","open":5810,"high":5871,"low":5731,"close":5794,"volume":40992,"adjusted":5794,"daily_return":0.002422,"cum_return":0.277644},{"date":"2025-06-27","open":5821,"high":5990,"low":5778,"close":5945,"volume":29330,"adjusted":5945,"daily_return":0.026061,"cum_return":0.310941},{"date":"2025-07-04","open":5949,"high":5974,"low":5883,"close":5907,"volume":19292,"adjusted":5907,"daily_return":-0.006392,"cum_return":0.302562},{"date":"2025-07-11","open":5922,"high":6037,"low":5922,"close":6035,"volume":20105,"adjusted":6035,"daily_return":0.021669,"cum_return":0.330787},{"date":"2025-07-18","open":5993,"high":6135,"low":5990,"close":6073,"volume":206724,"adjusted":6073,"daily_return":0.006297,"cum_return":0.339167},{"date":"2025-07-25","open":6082,"high":6122,"low":5957,"close":6103,"volume":26262,"adjusted":6103,"daily_return":0.00494,"cum_return":0.345782},{"date":"2025-08-01","open":6147,"high":6750,"low":6100,"close":6750,"volume":1317620,"adjusted":6750,"daily_return":0.106013,"cum_return":0.488453},{"date":"2025-08-08","open":6560,"high":6560,"low":6053,"close":6084,"volume":42591,"adjusted":6084,"daily_return":-0.098667,"cum_return":0.341592},{"date":"2025-08-15","open":6116,"high":6177,"low":6065,"close":6106,"volume":15901,"adjusted":6106,"daily_return":0.003616,"cum_return":0.346443},{"date":"2025-08-22","open":6167,"high":6171,"low":6087,"close":6155,"volume":16497,"adjusted":6155,"daily_return":0.008025,"cum_return":0.357248},{"date":"2025-08-29","open":6316,"high":6316,"low":6086,"close":6131,"volume":74004,"adjusted":6131,"daily_return":-0.003899,"cum_return":0.351956},{"date":"2025-09-05","open":6143,"high":6223,"low":6084,"close":6162,"volume":91524,"adjusted":6162,"daily_return":0.005056,"cum_return":0.358792},{"date":"2025-09-12","open":6218,"high":6362,"low":6204,"close":6326,"volume":117019,"adjusted":6326,"daily_return":0.026615,"cum_return":0.394956},{"date":"2025-09-19","open":6360,"high":6463,"low":6341,"close":6407,"volume":112312,"adjusted":6407,"daily_return":0.012804,"cum_return":0.412817},{"date":"2025-09-26","open":6405,"high":6453,"low":6346,"close":6347,"volume":16765,"adjusted":6347,"daily_return":-0.009365,"cum_return":0.399587},{"date":"2025-10-03","open":6411,"high":6554,"low":6374,"close":6525,"volume":52435,"adjusted":6525,"daily_return":0.028045,"cum_return":0.438838},{"date":"2025-10-10","open":6539,"high":6566,"low":6444,"close":6499,"volume":10741,"adjusted":6499,"daily_return":-0.003985,"cum_return":0.433104},{"date":"2025-10-17","open":6412,"high":6595,"low":6385,"close":6553,"volume":97012,"adjusted":6553,"daily_return":0.008309,"cum_return":0.445012},{"date":"2025-10-24","open":6568,"high":6641,"low":6528.1201,"close":6528.1201,"volume":45363,"adjusted":6528.1201,"daily_return":-0.003797,"cum_return":0.439526},{"date":"2025-10-31","open":6682,"high":6713,"low":6611,"close":6658,"volume":139233,"adjusted":6658,"daily_return":0.019895,"cum_return":0.468166},{"date":"2025-11-07","open":6702,"high":6717,"low":6522,"close":6523,"volume":9126,"adjusted":6523,"daily_return":-0.020276,"cum_return":0.438397},{"date":"2025-11-14","open":6601,"high":6652,"low":6451,"close":6538,"volume":48861,"adjusted":6538,"daily_return":0.0023,"cum_return":0.441704},{"date":"2025-11-21","open":6535,"high":6535,"low":6354,"close":6371,"volume":26764,"adjusted":6371,"daily_return":-0.025543,"cum_return":0.404879},{"date":"2025-11-28","open":6417,"high":6650,"low":6352,"close":6435,"volume":54009,"adjusted":6435,"daily_return":0.010046,"cum_return":0.418992},{"date":"2025-12-05","open":6442,"high":6484,"low":6410,"close":6456,"volume":12271,"adjusted":6456,"daily_return":0.003263,"cum_return":0.423622},{"date":"2025-12-12","open":6469,"high":6489,"low":6414,"close":6412,"volume":40513,"adjusted":6412,"daily_return":-0.006815,"cum_return":0.41392},{"date":"2025-12-19","open":6375,"high":6375,"low":6229,"close":6331,"volume":79690,"adjusted":6331,"daily_return":-0.012633,"cum_return":0.396059},{"date":"2025-12-24","open":6363,"high":6418,"low":6315,"close":6372,"volume":21741,"adjusted":6372,"daily_return":0.006476,"cum_return":0.4051},{"date":"2026-01-02","open":6436,"high":6522,"low":6359,"close":6504,"volume":51636,"adjusted":6504,"daily_return":0.020716,"cum_return":0.434207},{"date":"2026-01-09","open":6586,"high":6620,"low":6498,"close":6591,"volume":6808,"adjusted":6591,"daily_return":0.013376,"cum_return":0.453392},{"date":"2026-01-16","open":6580,"high":6750,"low":6556,"close":6640,"volume":41109,"adjusted":6640,"daily_return":0.007434,"cum_return":0.464197},{"date":"2026-01-23","open":6660,"high":6692,"low":6576,"close":6637,"volume":130223,"adjusted":6637,"daily_return":-0.000452,"cum_return":0.463535},{"date":"2026-01-30","open":6632,"high":6788,"low":6584,"close":6695,"volume":30418,"adjusted":6695,"daily_return":0.008739,"cum_return":0.476325},{"date":"2026-02-06","open":6605,"high":6779,"low":6580,"close":6709,"volume":81042,"adjusted":6709,"daily_return":0.002091,"cum_return":0.479412},{"date":"2026-02-13","open":6753,"high":6914,"low":6696,"close":6797,"volume":106081,"adjusted":6797,"daily_return":0.013117,"cum_return":0.498817},{"date":"2026-02-20","open":6865,"high":6970,"low":6826,"close":6919,"volume":111896,"adjusted":6919,"daily_return":0.017949,"cum_return":0.525719},{"date":"2026-02-27","open":6970,"high":7200,"low":6938,"close":6964,"volume":35170,"adjusted":6964,"daily_return":0.006504,"cum_return":0.535642},{"date":"2026-03-06","open":6963,"high":6964,"low":6626,"close":6648,"volume":119634,"adjusted":6648,"daily_return":-0.045376,"cum_return":0.465961},{"date":"2026-03-13","open":6583,"high":6775,"low":6544,"close":6710,"volume":73877,"adjusted":6710,"daily_return":0.009326,"cum_return":0.479632},{"date":"2026-03-20","open":6711,"high":6908,"low":6686,"close":6672,"volume":26652,"adjusted":6672,"daily_return":-0.005663,"cum_return":0.471253},{"date":"2026-03-27","open":6601,"high":6817,"low":6568,"close":6586,"volume":126304,"adjusted":6586,"daily_return":-0.01289,"cum_return":0.452289},{"date":"2026-04-02","open":6619,"high":6731,"low":6482,"close":6674,"volume":29851,"adjusted":6674,"daily_return":0.013362,"cum_return":0.471694},{"date":"2026-04-10","open":6763,"high":6968,"low":6686,"close":6944,"volume":15470,"adjusted":6944,"daily_return":0.040455,"cum_return":0.531232},{"date":"2026-04-17","open":6950,"high":7208,"low":6903,"close":7245,"volume":13944,"adjusted":7245,"daily_return":0.043347,"cum_return":0.597606},{"date":"2026-04-24","open":7197,"high":7339,"low":7156,"close":7280,"volume":17638,"adjusted":7280,"daily_return":0.004831,"cum_return":0.605324},{"date":"2026-04-30","open":7312,"high":7403,"low":7213,"close":7327,"volume":48146,"adjusted":7327,"daily_return":0.006456,"cum_return":0.615688},{"date":"2026-05-08","open":7436,"high":7697,"low":7423,"close":7690,"volume":142871,"adjusted":7690,"daily_return":0.049543,"cum_return":0.695734}],"monthly_returns":[{"year":2020,"month_num":9,"return":-0.008995},{"year":2020,"month_num":10,"return":-0.016159},{"year":2020,"month_num":11,"return":0.033601},{"year":2020,"month_num":12,"return":0.019379},{"year":2021,"month_num":1,"return":0.050446},{"year":2021,"month_num":2,"return":-0.018869},{"year":2021,"month_num":3,"return":-0.037434},{"year":2021,"month_num":4,"return":-0.000049},{"year":2021,"month_num":5,"return":-0.033641},{"year":2021,"month_num":6,"return":0.031069},{"year":2021,"month_num":7,"return":-0.0499},{"year":2021,"month_num":8,"return":0.022753},{"year":2021,"month_num":9,"return":0.00148},{"year":2021,"month_num":10,"return":0.03664},{"year":2021,"month_num":11,"return":-0.002856},{"year":2021,"month_num":12,"return":0.003257},{"year":2022,"month_num":1,"return":-0.037327},{"year":2022,"month_num":2,"return":-0.029225},{"year":2022,"month_num":3,"return":-0.059711},{"year":2022,"month_num":4,"return":0.011073},{"year":2022,"month_num":5,"return":-0.005688},{"year":2022,"month_num":6,"return":-0.008952},{"year":2022,"month_num":7,"return":0.014326},{"year":2022,"month_num":8,"return":0.032779},{"year":2022,"month_num":9,"return":-0.069304},{"year":2022,"month_num":10,"return":0.002915},{"year":2022,"month_num":11,"return":0.044041},{"year":2022,"month_num":12,"return":-0.05544},{"year":2023,"month_num":1,"return":0.10327},{"year":2023,"month_num":2,"return":-0.017151},{"year":2023,"month_num":3,"return":-0.013203},{"year":2023,"month_num":4,"return":0.013058},{"year":2023,"month_num":5,"return":0.062382},{"year":2023,"month_num":6,"return":-0.003987},{"year":2023,"month_num":7,"return":-0.007926},{"year":2023,"month_num":8,"return":-0.025176},{"year":2023,"month_num":9,"return":-0.033375},{"year":2023,"month_num":10,"return":-0.055129},{"year":2023,"month_num":11,"return":0.091914},{"year":2023,"month_num":12,"return":0.020974},{"year":2024,"month_num":1,"return":-0.043816},{"year":2024,"month_num":2,"return":0.071012},{"year":2024,"month_num":3,"return":0.006485},{"year":2024,"month_num":4,"return":-0.003154},{"year":2024,"month_num":5,"return":0.007732},{"year":2024,"month_num":6,"return":0.012119},{"year":2024,"month_num":7,"return":0.012065},{"year":2024,"month_num":8,"return":-0.014737},{"year":2024,"month_num":9,"return":0.031002},{"year":2024,"month_num":10,"return":-0.0254},{"year":2024,"month_num":11,"return":-0.010573},{"year":2024,"month_num":12,"return":0.019537},{"year":2025,"month_num":1,"return":0.01346},{"year":2025,"month_num":2,"return":0},{"year":2025,"month_num":3,"return":-0.012603},{"year":2025,"month_num":4,"return":0.019114},{"year":2025,"month_num":5,"return":-0.003011},{"year":2025,"month_num":6,"return":0.062131},{"year":2025,"month_num":7,"return":0.036173},{"year":2025,"month_num":8,"return":-0.091704},{"year":2025,"month_num":9,"return":0.051668},{"year":2025,"month_num":10,"return":0.038366},{"year":2025,"month_num":11,"return":-0.038691},{"year":2025,"month_num":12,"return":-0.001555},{"year":2026,"month_num":1,"return":0.029367},{"year":2026,"month_num":2,"return":0.059647},{"year":2026,"month_num":3,"return":-0.051582},{"year":2026,"month_num":4,"return":0.088869},{"year":2026,"month_num":5,"return":0.029865}],"rolling_vol":[{"date":"2020-09-11","vol_30d":null,"vol_90d":null,"vol_252d":null},{"date":"2020-09-18","vol_30d":null,"vol_90d":null,"vol_252d":null},{"date":"2020-09-25","vol_30d":null,"vol_90d":null,"vol_252d":null},{"date":"2020-10-02","vol_30d":null,"vol_90d":null,"vol_252d":null},{"date":"2020-10-09","vol_30d":null,"vol_90d":null,"vol_252d":null},{"date":"2020-10-16","vol_30d":null,"vol_90d":null,"vol_252d":null},{"date":"2020-10-23","vol_30d":0.163785,"vol_90d":null,"vol_252d":null},{"date":"2020-10-30","vol_30d":0.175416,"vol_90d":null,"vol_252d":null},{"date":"2020-11-06","vol_30d":0.173089,"vol_90d":null,"vol_252d":null},{"date":"2020-11-13","vol_30d":0.166246,"vol_90d":null,"vol_252d":null},{"date":"2020-11-20","vol_30d":0.158221,"vol_90d":null,"vol_252d":null},{"date":"2020-11-27","vol_30d":0.167562,"vol_90d":null,"vol_252d":null},{"date":"2020-12-04","vol_30d":0.169451,"vol_90d":null,"vol_252d":null},{"date":"2020-12-11","vol_30d":0.152303,"vol_90d":null,"vol_252d":null},{"date":"2020-12-18","vol_30d":0.144219,"vol_90d":null,"vol_252d":null},{"date":"2020-12-24","vol_30d":0.122958,"vol_90d":null,"vol_252d":null},{"date":"2020-12-31","vol_30d":0.135798,"vol_90d":null,"vol_252d":null},{"date":"2021-01-08","vol_30d":0.174502,"vol_90d":null,"vol_252d":null},{"date":"2021-01-15","vol_30d":0.173588,"vol_90d":null,"vol_252d":null},{"date":"2021-01-22","vol_30d":0.169622,"vol_90d":0.16787,"vol_252d":null},{"date":"2021-01-29","vol_30d":0.212156,"vol_90d":0.180511,"vol_252d":null},{"date":"2021-02-05","vol_30d":0.216425,"vol_90d":0.178329,"vol_252d":null},{"date":"2021-02-12","vol_30d":0.213292,"vol_90d":0.172506,"vol_252d":null},{"date":"2021-02-19","vol_30d":0.190886,"vol_90d":0.177336,"vol_252d":null},{"date":"2021-02-26","vol_30d":0.216191,"vol_90d":0.187972,"vol_252d":null},{"date":"2021-03-05","vol_30d":0.225099,"vol_90d":0.1893,"vol_252d":null},{"date":"2021-03-12","vol_30d":0.194368,"vol_90d":0.185794,"vol_252d":null},{"date":"2021-03-19","vol_30d":0.176767,"vol_90d":0.178981,"vol_252d":null},{"date":"2021-03-26","vol_30d":0.182892,"vol_90d":0.181048,"vol_252d":null},{"date":"2021-04-01","vol_30d":0.171833,"vol_90d":0.182417,"vol_252d":null},{"date":"2021-04-09","vol_30d":0.158147,"vol_90d":0.179731,"vol_252d":null},{"date":"2021-04-16","vol_30d":0.14285,"vol_90d":0.181399,"vol_252d":null},{"date":"2021-04-23","vol_30d":0.119215,"vol_90d":0.181572,"vol_252d":null},{"date":"2021-04-30","vol_30d":0.115434,"vol_90d":0.17894,"vol_252d":null},{"date":"2021-05-07","vol_30d":0.114544,"vol_90d":0.17819,"vol_252d":null},{"date":"2021-05-14","vol_30d":0.126223,"vol_90d":0.179656,"vol_252d":null},{"date":"2021-05-21","vol_30d":0.121707,"vol_90d":0.160391,"vol_252d":null},{"date":"2021-05-28","vol_30d":0.121817,"vol_90d":0.161623,"vol_252d":null},{"date":"2021-06-04","vol_30d":0.13806,"vol_90d":0.162532,"vol_252d":null},{"date":"2021-06-11","vol_30d":0.135834,"vol_90d":0.144845,"vol_252d":null},{"date":"2021-06-18","vol_30d":0.140066,"vol_90d":0.146143,"vol_252d":null},{"date":"2021-06-25","vol_30d":0.126068,"vol_90d":0.147646,"vol_252d":null},{"date":"2021-07-02","vol_30d":0.135908,"vol_90d":0.144244,"vol_252d":null},{"date":"2021-07-09","vol_30d":0.149733,"vol_90d":0.135189,"vol_252d":null},{"date":"2021-07-16","vol_30d":0.155437,"vol_90d":0.139666,"vol_252d":null},{"date":"2021-07-23","vol_30d":0.159957,"vol_90d":0.137875,"vol_252d":null},{"date":"2021-07-30","vol_30d":0.186403,"vol_90d":0.149556,"vol_252d":null},{"date":"2021-08-06","vol_30d":0.18991,"vol_90d":0.149955,"vol_252d":null},{"date":"2021-08-13","vol_30d":0.19627,"vol_90d":0.152481,"vol_252d":null},{"date":"2021-08-20","vol_30d":0.181124,"vol_90d":0.15207,"vol_252d":null},{"date":"2021-08-27","vol_30d":0.166504,"vol_90d":0.151517,"vol_252d":null},{"date":"2021-09-03","vol_30d":0.166211,"vol_90d":0.153377,"vol_252d":null},{"date":"2021-09-10","vol_30d":0.149004,"vol_90d":0.158097,"vol_252d":null},{"date":"2021-09-17","vol_30d":0.150878,"vol_90d":0.156977,"vol_252d":0.16557},{"date":"2021-09-23","vol_30d":0.144219,"vol_90d":0.156636,"vol_252d":0.164958},{"date":"2021-10-01","vol_30d":0.16256,"vol_90d":0.16287,"vol_252d":0.164393},{"date":"2021-10-08","vol_30d":0.157677,"vol_90d":0.157513,"vol_252d":0.162088},{"date":"2021-10-15","vol_30d":0.149097,"vol_90d":0.157398,"vol_252d":0.162431},{"date":"2021-10-22","vol_30d":0.134716,"vol_90d":0.158551,"vol_252d":0.162289},{"date":"2021-10-29","vol_30d":0.133311,"vol_90d":0.156178,"vol_252d":0.161897},{"date":"2021-11-05","vol_30d":0.138006,"vol_90d":0.15783,"vol_252d":0.160047},{"date":"2021-11-12","vol_30d":0.131677,"vol_90d":0.16029,"vol_252d":0.158624},{"date":"2021-11-19","vol_30d":0.138848,"vol_90d":0.15445,"vol_252d":0.160484},{"date":"2021-11-26","vol_30d":0.133395,"vol_90d":0.150933,"vol_252d":0.159112},{"date":"2021-12-03","vol_30d":0.1465,"vol_90d":0.142425,"vol_252d":0.159759},{"date":"2021-12-10","vol_30d":0.16375,"vol_90d":0.147343,"vol_252d":0.161308},{"date":"2021-12-17","vol_30d":0.164004,"vol_90d":0.145584,"vol_252d":0.161551},{"date":"2021-12-24","vol_30d":0.171445,"vol_90d":0.153449,"vol_252d":0.163795},{"date":"2021-12-31","vol_30d":0.163392,"vol_90d":0.155941,"vol_252d":0.164146},{"date":"2022-01-07","vol_30d":0.18708,"vol_90d":0.160859,"vol_252d":0.162783},{"date":"2022-01-14","vol_30d":0.186331,"vol_90d":0.158956,"vol_252d":0.159907},{"date":"2022-01-17","vol_30d":0.184232,"vol_90d":0.158817,"vol_252d":0.159883},{"date":"2022-01-28","vol_30d":0.174389,"vol_90d":0.156519,"vol_252d":0.160835},{"date":"2022-02-04","vol_30d":0.189787,"vol_90d":0.16349,"vol_252d":0.158947},{"date":"2022-02-11","vol_30d":0.16998,"vol_90d":0.15798,"vol_252d":0.15583},{"date":"2022-02-18","vol_30d":0.171751,"vol_90d":0.159018,"vol_252d":0.156968},{"date":"2022-02-25","vol_30d":0.158425,"vol_90d":0.162721,"vol_252d":0.156287},{"date":"2022-03-04","vol_30d":0.162814,"vol_90d":0.16539,"vol_252d":0.153641},{"date":"2022-03-11","vol_30d":0.201075,"vol_90d":0.182009,"vol_252d":0.159366},{"date":"2022-03-18","vol_30d":0.263613,"vol_90d":0.209854,"vol_252d":0.169807},{"date":"2022-03-25","vol_30d":0.263466,"vol_90d":0.206603,"vol_252d":0.170642},{"date":"2022-04-01","vol_30d":0.262155,"vol_90d":0.202689,"vol_252d":0.170372},{"date":"2022-04-08","vol_30d":0.257989,"vol_90d":0.204364,"vol_252d":0.170102},{"date":"2022-04-14","vol_30d":0.26569,"vol_90d":0.206465,"vol_252d":0.171443},{"date":"2022-04-22","vol_30d":0.235714,"vol_90d":0.206468,"vol_252d":0.171682},{"date":"2022-04-29","vol_30d":0.225547,"vol_90d":0.207188,"vol_252d":0.172728},{"date":"2022-05-06","vol_30d":0.168183,"vol_90d":0.210674,"vol_252d":0.174657},{"date":"2022-05-13","vol_30d":0.185377,"vol_90d":0.2111,"vol_252d":0.17747},{"date":"2022-05-20","vol_30d":0.211366,"vol_90d":0.217388,"vol_252d":0.180479},{"date":"2022-05-27","vol_30d":0.212125,"vol_90d":0.213245,"vol_252d":0.180596},{"date":"2022-06-03","vol_30d":0.223101,"vol_90d":0.218544,"vol_252d":0.182532},{"date":"2022-06-10","vol_30d":0.214791,"vol_90d":0.219184,"vol_252d":0.181684},{"date":"2022-06-17","vol_30d":0.222866,"vol_90d":0.219928,"vol_252d":0.182798},{"date":"2022-06-24","vol_30d":0.206607,"vol_90d":0.217547,"vol_252d":0.184017},{"date":"2022-07-01","vol_30d":0.185842,"vol_90d":0.218252,"vol_252d":0.184301},{"date":"2022-07-08","vol_30d":0.174035,"vol_90d":0.218101,"vol_252d":0.185133},{"date":"2022-07-15","vol_30d":0.174428,"vol_90d":0.221351,"vol_252d":0.186189},{"date":"2022-07-22","vol_30d":0.182997,"vol_90d":0.211276,"vol_252d":0.184378},{"date":"2022-07-29","vol_30d":0.166217,"vol_90d":0.180908,"vol_252d":0.18381},{"date":"2022-08-05","vol_30d":0.165244,"vol_90d":0.181567,"vol_252d":0.181382},{"date":"2022-08-12","vol_30d":0.195549,"vol_90d":0.19329,"vol_252d":0.185642},{"date":"2022-08-19","vol_30d":0.194014,"vol_90d":0.193928,"vol_252d":0.184822},{"date":"2022-08-26","vol_30d":0.183326,"vol_90d":0.191553,"vol_252d":0.185101},{"date":"2022-09-02","vol_30d":0.173652,"vol_90d":0.188726,"vol_252d":0.184815},{"date":"2022-09-09","vol_30d":0.168487,"vol_90d":0.186394,"vol_252d":0.183632},{"date":"2022-09-16","vol_30d":0.172101,"vol_90d":0.183329,"vol_252d":0.184492},{"date":"2022-09-23","vol_30d":0.133068,"vol_90d":0.178467,"vol_252d":0.184171},{"date":"2022-09-30","vol_30d":0.127361,"vol_90d":0.167999,"vol_252d":0.184462},{"date":"2022-10-07","vol_30d":0.155734,"vol_90d":0.169037,"vol_252d":0.184962},{"date":"2022-10-14","vol_30d":0.171269,"vol_90d":0.173651,"vol_252d":0.186277},{"date":"2022-10-21","vol_30d":0.180214,"vol_90d":0.173312,"vol_252d":0.187017},{"date":"2022-10-28","vol_30d":0.173875,"vol_90d":0.17021,"vol_252d":0.187857},{"date":"2022-11-04","vol_30d":0.182385,"vol_90d":0.170718,"vol_252d":0.188842},{"date":"2022-11-11","vol_30d":0.22933,"vol_90d":0.188488,"vol_252d":0.194795},{"date":"2022-11-18","vol_30d":0.222538,"vol_90d":0.187678,"vol_252d":0.194535},{"date":"2022-11-25","vol_30d":0.213669,"vol_90d":0.186202,"vol_252d":0.193872},{"date":"2022-12-02","vol_30d":0.248481,"vol_90d":0.202376,"vol_252d":0.200544},{"date":"2022-12-09","vol_30d":0.259475,"vol_90d":0.207563,"vol_252d":0.20241},{"date":"2022-12-15","vol_30d":0.261415,"vol_90d":0.198197,"vol_252d":0.201529},{"date":"2022-12-23","vol_30d":0.255519,"vol_90d":0.199853,"vol_252d":0.202153},{"date":"2022-12-30","vol_30d":0.225973,"vol_90d":0.201936,"vol_252d":0.200766},{"date":"2023-01-06","vol_30d":0.242171,"vol_90d":0.209156,"vol_252d":0.202746},{"date":"2023-01-13","vol_30d":0.236166,"vol_90d":0.209594,"vol_252d":0.201116},{"date":"2023-01-20","vol_30d":0.204229,"vol_90d":0.212915,"vol_252d":0.202178},{"date":"2023-01-27","vol_30d":0.181067,"vol_90d":0.210411,"vol_252d":0.202237},{"date":"2023-02-03","vol_30d":0.171329,"vol_90d":0.208604,"vol_252d":0.201975},{"date":"2023-02-10","vol_30d":0.15231,"vol_90d":0.207703,"vol_252d":0.200633},{"date":"2023-02-17","vol_30d":0.142158,"vol_90d":0.204286,"vol_252d":0.200621},{"date":"2023-02-24","vol_30d":0.150242,"vol_90d":0.202239,"vol_252d":0.200544},{"date":"2023-03-03","vol_30d":0.140325,"vol_90d":0.199441,"vol_252d":0.200411},{"date":"2023-03-10","vol_30d":0.171873,"vol_90d":0.20648,"vol_252d":0.198554},{"date":"2023-03-17","vol_30d":0.184979,"vol_90d":0.210771,"vol_252d":0.196465},{"date":"2023-03-24","vol_30d":0.180269,"vol_90d":0.193044,"vol_252d":0.188842},{"date":"2023-03-31","vol_30d":0.177413,"vol_90d":0.188989,"vol_252d":0.187871},{"date":"2023-04-06","vol_30d":0.164346,"vol_90d":0.186329,"vol_252d":0.187762},{"date":"2023-04-14","vol_30d":0.171888,"vol_90d":0.184429,"vol_252d":0.188628},{"date":"2023-04-21","vol_30d":0.175272,"vol_90d":0.169904,"vol_252d":0.188554},{"date":"2023-04-28","vol_30d":0.141063,"vol_90d":0.161916,"vol_252d":0.186977},{"date":"2023-05-05","vol_30d":0.130096,"vol_90d":0.164824,"vol_252d":0.187234},{"date":"2023-05-12","vol_30d":0.145134,"vol_90d":0.161602,"vol_252d":0.186375},{"date":"2023-05-19","vol_30d":0.148058,"vol_90d":0.154271,"vol_252d":0.184166},{"date":"2023-05-26","vol_30d":0.15204,"vol_90d":0.155904,"vol_252d":0.18061},{"date":"2023-06-02","vol_30d":0.141374,"vol_90d":0.154066,"vol_252d":0.179823},{"date":"2023-06-09","vol_30d":0.150567,"vol_90d":0.157134,"vol_252d":0.180178},{"date":"2023-06-15","vol_30d":0.166708,"vol_90d":0.160376,"vol_252d":0.181242},{"date":"2023-06-23","vol_30d":0.15665,"vol_90d":0.159848,"vol_252d":0.17993},{"date":"2023-06-30","vol_30d":0.151404,"vol_90d":0.159813,"vol_252d":0.179075},{"date":"2023-07-07","vol_30d":0.152903,"vol_90d":0.157864,"vol_252d":0.178652},{"date":"2023-07-14","vol_30d":0.152705,"vol_90d":0.156239,"vol_252d":0.17836},{"date":"2023-07-21","vol_30d":0.143861,"vol_90d":0.156915,"vol_252d":0.177153},{"date":"2023-07-28","vol_30d":0.13356,"vol_90d":0.144571,"vol_252d":0.176313},{"date":"2023-08-04","vol_30d":0.147105,"vol_90d":0.14562,"vol_252d":0.177974},{"date":"2023-08-11","vol_30d":0.151107,"vol_90d":0.148772,"vol_252d":0.177744},{"date":"2023-08-18","vol_30d":0.156019,"vol_90d":0.151388,"vol_252d":0.17355},{"date":"2023-08-25","vol_30d":0.170969,"vol_90d":0.154056,"vol_252d":0.175133},{"date":"2023-09-01","vol_30d":0.161095,"vol_90d":0.151453,"vol_252d":0.175106},{"date":"2023-09-08","vol_30d":0.171644,"vol_90d":0.157914,"vol_252d":0.17655},{"date":"2023-09-15","vol_30d":0.170014,"vol_90d":0.157513,"vol_252d":0.177636},{"date":"2023-09-22","vol_30d":0.167173,"vol_90d":0.155116,"vol_252d":0.177478},{"date":"2023-09-29","vol_30d":0.169051,"vol_90d":0.154792,"vol_252d":0.176593},{"date":"2023-10-06","vol_30d":0.159463,"vol_90d":0.155728,"vol_252d":0.176788},{"date":"2023-10-13","vol_30d":0.157309,"vol_90d":0.155298,"vol_252d":0.175107},{"date":"2023-10-20","vol_30d":0.150261,"vol_90d":0.15618,"vol_252d":0.174204},{"date":"2023-10-27","vol_30d":0.149169,"vol_90d":0.152552,"vol_252d":0.174107},{"date":"2023-11-03","vol_30d":0.140823,"vol_90d":0.152389,"vol_252d":0.173567},{"date":"2023-11-10","vol_30d":0.155539,"vol_90d":0.156952,"vol_252d":0.173529},{"date":"2023-11-17","vol_30d":0.151413,"vol_90d":0.157699,"vol_252d":0.171705},{"date":"2023-11-24","vol_30d":0.15231,"vol_90d":0.155547,"vol_252d":0.166356},{"date":"2023-12-01","vol_30d":0.165155,"vol_90d":0.162702,"vol_252d":0.168039},{"date":"2023-12-08","vol_30d":0.156988,"vol_90d":0.158838,"vol_252d":0.161195},{"date":"2023-12-14","vol_30d":0.163956,"vol_90d":0.158049,"vol_252d":0.16011},{"date":"2023-12-22","vol_30d":0.16689,"vol_90d":0.162751,"vol_252d":0.159313},{"date":"2023-12-29","vol_30d":0.175785,"vol_90d":0.165617,"vol_252d":0.160555},{"date":"2024-01-05","vol_30d":0.171921,"vol_90d":0.159032,"vol_252d":0.158932},{"date":"2024-01-12","vol_30d":0.164157,"vol_90d":0.157395,"vol_252d":0.154726},{"date":"2024-01-19","vol_30d":0.148365,"vol_90d":0.154804,"vol_252d":0.155383},{"date":"2024-01-26","vol_30d":0.146717,"vol_90d":0.151214,"vol_252d":0.153708},{"date":"2024-02-02","vol_30d":0.148003,"vol_90d":0.15656,"vol_252d":0.156294},{"date":"2024-02-09","vol_30d":0.133488,"vol_90d":0.152465,"vol_252d":0.156138},{"date":"2024-02-16","vol_30d":0.130155,"vol_90d":0.151476,"vol_252d":0.154502},{"date":"2024-02-23","vol_30d":0.140275,"vol_90d":0.149706,"vol_252d":0.155628},{"date":"2024-03-01","vol_30d":0.130626,"vol_90d":0.146774,"vol_252d":0.15338},{"date":"2024-03-08","vol_30d":0.141572,"vol_90d":0.148253,"vol_252d":0.154131},{"date":"2024-03-15","vol_30d":0.117031,"vol_90d":0.143733,"vol_252d":0.153616},{"date":"2024-03-22","vol_30d":0.135182,"vol_90d":0.149003,"vol_252d":0.150148},{"date":"2024-03-28","vol_30d":0.132898,"vol_90d":0.145514,"vol_252d":0.148677},{"date":"2024-04-05","vol_30d":0.137997,"vol_90d":0.14404,"vol_252d":0.149358},{"date":"2024-04-12","vol_30d":0.123897,"vol_90d":0.142833,"vol_252d":0.149387},{"date":"2024-04-19","vol_30d":0.135481,"vol_90d":0.139841,"vol_252d":0.14949},{"date":"2024-04-26","vol_30d":0.160497,"vol_90d":0.150172,"vol_252d":0.151892},{"date":"2024-05-03","vol_30d":0.155979,"vol_90d":0.141355,"vol_252d":0.152246},{"date":"2024-05-10","vol_30d":0.147618,"vol_90d":0.137006,"vol_252d":0.150902},{"date":"2024-05-17","vol_30d":0.145098,"vol_90d":0.135708,"vol_252d":0.148782},{"date":"2024-05-24","vol_30d":0.149279,"vol_90d":0.137183,"vol_252d":0.148724},{"date":"2024-05-31","vol_30d":0.137928,"vol_90d":0.134209,"vol_252d":0.147665},{"date":"2024-06-07","vol_30d":0.140549,"vol_90d":0.143233,"vol_252d":0.15094},{"date":"2024-06-14","vol_30d":0.132336,"vol_90d":0.135515,"vol_252d":0.149531},{"date":"2024-06-21","vol_30d":0.133355,"vol_90d":0.137252,"vol_252d":0.147326},{"date":"2024-06-28","vol_30d":0.152403,"vol_90d":0.143372,"vol_252d":0.149091},{"date":"2024-07-05","vol_30d":0.159637,"vol_90d":0.142996,"vol_252d":0.149831},{"date":"2024-07-12","vol_30d":0.158347,"vol_90d":0.142574,"vol_252d":0.149315},{"date":"2024-07-19","vol_30d":0.139055,"vol_90d":0.141612,"vol_252d":0.149317},{"date":"2024-07-26","vol_30d":0.136083,"vol_90d":0.141738,"vol_252d":0.148088},{"date":"2024-08-02","vol_30d":0.17876,"vol_90d":0.152151,"vol_252d":0.152964},{"date":"2024-08-08","vol_30d":0.174791,"vol_90d":0.157217,"vol_252d":0.15275},{"date":"2024-08-16","vol_30d":0.16865,"vol_90d":0.157337,"vol_252d":0.152381},{"date":"2024-08-23","vol_30d":0.166563,"vol_90d":0.15689,"vol_252d":0.151406},{"date":"2024-08-30","vol_30d":0.167204,"vol_90d":0.150512,"vol_252d":0.148758},{"date":"2024-09-06","vol_30d":0.159292,"vol_90d":0.142075,"vol_252d":0.146828},{"date":"2024-09-13","vol_30d":0.163403,"vol_90d":0.144702,"vol_252d":0.147465},{"date":"2024-09-20","vol_30d":0.104699,"vol_90d":0.145257,"vol_252d":0.145759},{"date":"2024-09-27","vol_30d":0.136111,"vol_90d":0.155458,"vol_252d":0.148542},{"date":"2024-10-04","vol_30d":0.152684,"vol_90d":0.158938,"vol_252d":0.148888},{"date":"2024-10-11","vol_30d":0.15521,"vol_90d":0.158903,"vol_252d":0.14889},{"date":"2024-10-18","vol_30d":0.159978,"vol_90d":0.152185,"vol_252d":0.148003},{"date":"2024-10-25","vol_30d":0.160005,"vol_90d":0.155023,"vol_252d":0.148029},{"date":"2024-11-01","vol_30d":0.166642,"vol_90d":0.152406,"vol_252d":0.148314},{"date":"2024-11-08","vol_30d":0.135849,"vol_90d":0.147187,"vol_252d":0.145961},{"date":"2024-11-15","vol_30d":0.129816,"vol_90d":0.150468,"vol_252d":0.147487},{"date":"2024-11-22","vol_30d":0.129717,"vol_90d":0.150692,"vol_252d":0.146307},{"date":"2024-11-29","vol_30d":0.122298,"vol_90d":0.148288,"vol_252d":0.145726},{"date":"2024-12-06","vol_30d":0.133236,"vol_90d":0.151922,"vol_252d":0.144473},{"date":"2024-12-13","vol_30d":0.130645,"vol_90d":0.135075,"vol_252d":0.144906},{"date":"2024-12-20","vol_30d":0.130268,"vol_90d":0.13403,"vol_252d":0.142478},{"date":"2024-12-27","vol_30d":0.155027,"vol_90d":0.143237,"vol_252d":0.144924},{"date":"2025-01-03","vol_30d":0.146399,"vol_90d":0.143301,"vol_252d":0.143104},{"date":"2025-01-09","vol_30d":0.142759,"vol_90d":0.142136,"vol_252d":0.142657},{"date":"2025-01-17","vol_30d":0.145794,"vol_90d":0.144077,"vol_252d":0.143537},{"date":"2025-01-24","vol_30d":0.133352,"vol_90d":0.141528,"vol_252d":0.142752},{"date":"2025-01-31","vol_30d":0.134006,"vol_90d":0.143168,"vol_252d":0.143463},{"date":"2025-02-07","vol_30d":0.140462,"vol_90d":0.134635,"vol_252d":0.140742},{"date":"2025-02-14","vol_30d":0.106556,"vol_90d":0.128659,"vol_252d":0.140734},{"date":"2025-02-21","vol_30d":0.112455,"vol_90d":0.128505,"vol_252d":0.141024},{"date":"2025-02-28","vol_30d":0.144451,"vol_90d":0.13763,"vol_252d":0.143678},{"date":"2025-03-07","vol_30d":0.150622,"vol_90d":0.138002,"vol_252d":0.1448},{"date":"2025-03-14","vol_30d":0.162099,"vol_90d":0.141508,"vol_252d":0.1458},{"date":"2025-03-20","vol_30d":0.15918,"vol_90d":0.142569,"vol_252d":0.145626},{"date":"2025-03-28","vol_30d":0.165967,"vol_90d":0.141879,"vol_252d":0.144403},{"date":"2025-04-04","vol_30d":0.221998,"vol_90d":0.166455,"vol_252d":0.153794},{"date":"2025-04-11","vol_30d":0.248366,"vol_90d":0.179262,"vol_252d":0.159173},{"date":"2025-04-17","vol_30d":0.232035,"vol_90d":0.175562,"vol_252d":0.159659},{"date":"2025-04-25","vol_30d":0.234826,"vol_90d":0.178563,"vol_252d":0.159523},{"date":"2025-05-02","vol_30d":0.234484,"vol_90d":0.179974,"vol_252d":0.158046},{"date":"2025-05-09","vol_30d":0.241294,"vol_90d":0.183623,"vol_252d":0.158044},{"date":"2025-05-16","vol_30d":0.245218,"vol_90d":0.180514,"vol_252d":0.159449},{"date":"2025-05-23","vol_30d":0.189895,"vol_90d":0.182185,"vol_252d":0.15985},{"date":"2025-05-30","vol_30d":0.147405,"vol_90d":0.179531,"vol_252d":0.159196},{"date":"2025-06-06","vol_30d":0.130351,"vol_90d":0.179457,"vol_252d":0.159439},{"date":"2025-06-13","vol_30d":0.127582,"vol_90d":0.178419,"vol_252d":0.156773},{"date":"2025-06-20","vol_30d":0.119731,"vol_90d":0.177657,"vol_252d":0.156499},{"date":"2025-06-27","vol_30d":0.095983,"vol_90d":0.178668,"vol_252d":0.156351},{"date":"2025-07-04","vol_30d":0.087627,"vol_90d":0.177508,"vol_252d":0.154217},{"date":"2025-07-11","vol_30d":0.095707,"vol_90d":0.175361,"vol_252d":0.153678},{"date":"2025-07-18","vol_30d":0.091641,"vol_90d":0.166262,"vol_252d":0.153677},{"date":"2025-07-25","vol_30d":0.099772,"vol_90d":0.162275,"vol_252d":0.153272},{"date":"2025-08-01","vol_30d":0.300286,"vol_90d":0.231842,"vol_252d":0.182603},{"date":"2025-08-08","vol_30d":0.422812,"vol_90d":0.284644,"vol_252d":0.203454},{"date":"2025-08-15","vol_30d":0.423683,"vol_90d":0.269941,"vol_252d":0.202244},{"date":"2025-08-22","vol_30d":0.422252,"vol_90d":0.261387,"vol_252d":0.202204},{"date":"2025-08-29","vol_30d":0.422306,"vol_90d":0.260687,"vol_252d":0.202086},{"date":"2025-09-05","vol_30d":0.419865,"vol_90d":0.257898,"vol_252d":0.202115},{"date":"2025-09-12","vol_30d":0.296479,"vol_90d":0.254806,"vol_252d":0.201758},{"date":"2025-09-19","vol_30d":0.076721,"vol_90d":0.251371,"vol_252d":0.201107},{"date":"2025-09-26","vol_30d":0.079476,"vol_90d":0.251253,"vol_252d":0.201058},{"date":"2025-10-03","vol_30d":0.088039,"vol_90d":0.252521,"vol_252d":0.198983},{"date":"2025-10-10","vol_30d":0.088119,"vol_90d":0.251755,"vol_252d":0.197831},{"date":"2025-10-17","vol_30d":0.097005,"vol_90d":0.252681,"vol_252d":0.197647},{"date":"2025-10-24","vol_30d":0.098065,"vol_90d":0.251963,"vol_252d":0.197157},{"date":"2025-10-31","vol_30d":0.111716,"vol_90d":0.253402,"vol_252d":0.197296},{"date":"2025-11-07","vol_30d":0.123932,"vol_90d":0.256126,"vol_252d":0.197362},{"date":"2025-11-14","vol_30d":0.119105,"vol_90d":0.256333,"vol_252d":0.197506},{"date":"2025-11-21","vol_30d":0.13179,"vol_90d":0.257948,"vol_252d":0.197764},{"date":"2025-11-28","vol_30d":0.127204,"vol_90d":0.257096,"vol_252d":0.197736},{"date":"2025-12-05","vol_30d":0.126338,"vol_90d":0.257389,"vol_252d":0.195905},{"date":"2025-12-12","vol_30d":0.108913,"vol_90d":0.102223,"vol_252d":0.195764},{"date":"2025-12-19","vol_30d":0.122237,"vol_90d":0.106379,"vol_252d":0.196206},{"date":"2025-12-24","vol_30d":0.104235,"vol_90d":0.105748,"vol_252d":0.196298},{"date":"2026-01-02","vol_30d":0.110965,"vol_90d":0.107106,"vol_252d":0.194089},{"date":"2026-01-09","vol_30d":0.098218,"vol_90d":0.107632,"vol_252d":0.194341},{"date":"2026-01-16","vol_30d":0.095969,"vol_90d":0.107977,"vol_252d":0.193692},{"date":"2026-01-23","vol_30d":0.09508,"vol_90d":0.106688,"vol_252d":0.193127},{"date":"2026-01-30","vol_30d":0.11176,"vol_90d":0.113989,"vol_252d":0.194665},{"date":"2026-02-06","vol_30d":0.13072,"vol_90d":0.120886,"vol_252d":0.19567},{"date":"2026-02-13","vol_30d":0.134874,"vol_90d":0.1216,"vol_252d":0.196111},{"date":"2026-02-20","vol_30d":0.133596,"vol_90d":0.121615,"vol_252d":0.195992},{"date":"2026-02-27","vol_30d":0.137819,"vol_90d":0.120933,"vol_252d":0.195625},{"date":"2026-03-06","vol_30d":0.182756,"vol_90d":0.134414,"vol_252d":0.196509},{"date":"2026-03-13","vol_30d":0.178162,"vol_90d":0.138367,"vol_252d":0.196391},{"date":"2026-03-20","vol_30d":0.170329,"vol_90d":0.137577,"vol_252d":0.196633},{"date":"2026-03-27","vol_30d":0.180086,"vol_90d":0.144131,"vol_252d":0.19843},{"date":"2026-04-02","vol_30d":0.193053,"vol_90d":0.146691,"vol_252d":0.199175},{"date":"2026-04-10","vol_30d":0.214173,"vol_90d":0.155295,"vol_252d":0.194273},{"date":"2026-04-17","vol_30d":0.189172,"vol_90d":0.158372,"vol_252d":0.190811},{"date":"2026-04-24","vol_30d":0.17513,"vol_90d":0.158457,"vol_252d":0.189097},{"date":"2026-04-30","vol_30d":0.174587,"vol_90d":0.155774,"vol_252d":0.189476},{"date":"2026-05-08","vol_30d":0.171814,"vol_90d":0.160038,"vol_252d":0.189604}],"drawdown":[{"date":"2020-09-11","drawdown":0},{"date":"2020-09-18","drawdown":-0.028168},{"date":"2020-09-25","drawdown":-0.025101},{"date":"2020-10-02","drawdown":-0.030348},{"date":"2020-10-09","drawdown":0},{"date":"2020-10-16","drawdown":-0.008231},{"date":"2020-10-23","drawdown":-0.015195},{"date":"2020-10-30","drawdown":-0.046463},{"date":"2020-11-06","drawdown":-0.01964},{"date":"2020-11-13","drawdown":-0.009696},{"date":"2020-11-20","drawdown":-0.011482},{"date":"2020-11-27","drawdown":-0.000476},{"date":"2020-12-04","drawdown":0},{"date":"2020-12-11","drawdown":-0.002477},{"date":"2020-12-18","drawdown":-0.033255},{"date":"2020-12-24","drawdown":-0.040107},{"date":"2020-12-31","drawdown":-0.0036},{"date":"2021-01-08","drawdown":0},{"date":"2021-01-15","drawdown":-0.010362},{"date":"2021-01-22","drawdown":0},{"date":"2021-01-29","drawdown":-0.068236},{"date":"2021-02-05","drawdown":-0.03439},{"date":"2021-02-12","drawdown":-0.034342},{"date":"2021-02-19","drawdown":-0.029127},{"date":"2021-02-26","drawdown":-0.062662},{"date":"2021-03-05","drawdown":-0.044902},{"date":"2021-03-12","drawdown":-0.065242},{"date":"2021-03-19","drawdown":-0.087554},{"date":"2021-03-26","drawdown":-0.087344},{"date":"2021-04-01","drawdown":-0.091165},{"date":"2021-04-09","drawdown":-0.096843},{"date":"2021-04-16","drawdown":-0.102367},{"date":"2021-04-23","drawdown":-0.100719},{"date":"2021-04-30","drawdown":-0.091209},{"date":"2021-05-07","drawdown":-0.117207},{"date":"2021-05-14","drawdown":-0.139865},{"date":"2021-05-21","drawdown":-0.134913},{"date":"2021-05-28","drawdown":-0.124294},{"date":"2021-06-04","drawdown":-0.127789},{"date":"2021-06-11","drawdown":-0.114323},{"date":"2021-06-18","drawdown":-0.087448},{"date":"2021-06-25","drawdown":-0.087256},{"date":"2021-07-02","drawdown":-0.087883},{"date":"2021-07-09","drawdown":-0.115423},{"date":"2021-07-16","drawdown":-0.090426},{"date":"2021-07-23","drawdown":-0.083896},{"date":"2021-07-30","drawdown":-0.117135},{"date":"2021-08-06","drawdown":-0.103338},{"date":"2021-08-13","drawdown":-0.108866},{"date":"2021-08-20","drawdown":-0.11312},{"date":"2021-08-27","drawdown":-0.108403},{"date":"2021-09-03","drawdown":-0.110418},{"date":"2021-09-10","drawdown":-0.122635},{"date":"2021-09-17","drawdown":-0.104651},{"date":"2021-09-23","drawdown":-0.118924},{"date":"2021-10-01","drawdown":-0.117603},{"date":"2021-10-08","drawdown":-0.109597},{"date":"2021-10-15","drawdown":-0.10864},{"date":"2021-10-22","drawdown":-0.093291},{"date":"2021-10-29","drawdown":-0.085272},{"date":"2021-11-05","drawdown":-0.091089},{"date":"2021-11-12","drawdown":-0.066312},{"date":"2021-11-19","drawdown":-0.051915},{"date":"2021-11-26","drawdown":-0.056347},{"date":"2021-12-03","drawdown":-0.062567},{"date":"2021-12-10","drawdown":-0.059854},{"date":"2021-12-17","drawdown":-0.085483},{"date":"2021-12-24","drawdown":-0.101536},{"date":"2021-12-31","drawdown":-0.074181},{"date":"2022-01-07","drawdown":-0.091969},{"date":"2022-01-14","drawdown":-0.079774},{"date":"2022-01-21","drawdown":-0.105571},{"date":"2022-01-28","drawdown":-0.113599},{"date":"2022-02-04","drawdown":-0.100215},{"date":"2022-02-11","drawdown":-0.111708},{"date":"2022-02-18","drawdown":-0.114831},{"date":"2022-02-25","drawdown":-0.154736},{"date":"2022-03-04","drawdown":-0.176754},{"date":"2022-03-11","drawdown":-0.229802},{"date":"2022-03-18","drawdown":-0.199447},{"date":"2022-03-25","drawdown":-0.218704},{"date":"2022-04-01","drawdown":-0.200229},{"date":"2022-04-08","drawdown":-0.213287},{"date":"2022-04-14","drawdown":-0.220756},{"date":"2022-04-22","drawdown":-0.201353},{"date":"2022-04-29","drawdown":-0.191373},{"date":"2022-05-06","drawdown":-0.222469},{"date":"2022-05-13","drawdown":-0.228058},{"date":"2022-05-20","drawdown":-0.220235},{"date":"2022-05-27","drawdown":-0.229975},{"date":"2022-06-03","drawdown":-0.214265},{"date":"2022-06-10","drawdown":-0.209455},{"date":"2022-06-17","drawdown":-0.236401},{"date":"2022-06-24","drawdown":-0.236164},{"date":"2022-07-01","drawdown":-0.221289},{"date":"2022-07-08","drawdown":-0.196175},{"date":"2022-07-15","drawdown":-0.213794},{"date":"2022-07-22","drawdown":-0.20189},{"date":"2022-07-29","drawdown":-0.210133},{"date":"2022-08-05","drawdown":-0.195749},{"date":"2022-08-12","drawdown":-0.210046},{"date":"2022-08-19","drawdown":-0.184884},{"date":"2022-08-26","drawdown":-0.193614},{"date":"2022-09-02","drawdown":-0.205509},{"date":"2022-09-09","drawdown":-0.204938},{"date":"2022-09-16","drawdown":-0.21067},{"date":"2022-09-23","drawdown":-0.229973},{"date":"2022-09-30","drawdown":-0.252907},{"date":"2022-10-07","drawdown":-0.232162},{"date":"2022-10-14","drawdown":-0.25364},{"date":"2022-10-21","drawdown":-0.251179},{"date":"2022-10-28","drawdown":-0.269671},{"date":"2022-11-04","drawdown":-0.242288},{"date":"2022-11-11","drawdown":-0.23011},{"date":"2022-11-18","drawdown":-0.224965},{"date":"2022-11-25","drawdown":-0.230956},{"date":"2022-12-02","drawdown":-0.185528},{"date":"2022-12-09","drawdown":-0.188769},{"date":"2022-12-15","drawdown":-0.202579},{"date":"2022-12-23","drawdown":-0.22655},{"date":"2022-12-30","drawdown":-0.224385},{"date":"2023-01-06","drawdown":-0.189503},{"date":"2023-01-13","drawdown":-0.174215},{"date":"2023-01-20","drawdown":-0.150908},{"date":"2023-01-27","drawdown":-0.133717},{"date":"2023-02-03","drawdown":-0.132557},{"date":"2023-02-10","drawdown":-0.130954},{"date":"2023-02-17","drawdown":-0.140541},{"date":"2023-02-24","drawdown":-0.146208},{"date":"2023-03-03","drawdown":-0.148142},{"date":"2023-03-10","drawdown":-0.17495},{"date":"2023-03-17","drawdown":-0.16705},{"date":"2023-03-24","drawdown":-0.159081},{"date":"2023-03-31","drawdown":-0.161242},{"date":"2023-04-06","drawdown":-0.144319},{"date":"2023-04-14","drawdown":-0.135534},{"date":"2023-04-21","drawdown":-0.15466},{"date":"2023-04-28","drawdown":-0.149414},{"date":"2023-05-05","drawdown":-0.137978},{"date":"2023-05-12","drawdown":-0.101145},{"date":"2023-05-19","drawdown":-0.087402},{"date":"2023-05-26","drawdown":-0.087794},{"date":"2023-06-02","drawdown":-0.078366},{"date":"2023-06-09","drawdown":-0.100132},{"date":"2023-06-15","drawdown":-0.090234},{"date":"2023-06-23","drawdown":-0.104858},{"date":"2023-06-30","drawdown":-0.098223},{"date":"2023-07-07","drawdown":-0.105017},{"date":"2023-07-14","drawdown":-0.10038},{"date":"2023-07-21","drawdown":-0.119577},{"date":"2023-07-28","drawdown":-0.109745},{"date":"2023-08-04","drawdown":-0.090946},{"date":"2023-08-11","drawdown":-0.088757},{"date":"2023-08-18","drawdown":-0.116348},{"date":"2023-08-25","drawdown":-0.122577},{"date":"2023-09-01","drawdown":-0.106481},{"date":"2023-09-08","drawdown":-0.105256},{"date":"2023-09-15","drawdown":-0.091648},{"date":"2023-09-22","drawdown":-0.127718},{"date":"2023-09-29","drawdown":-0.136302},{"date":"2023-10-06","drawdown":-0.123392},{"date":"2023-10-13","drawdown":-0.127539},{"date":"2023-10-20","drawdown":-0.152073},{"date":"2023-10-27","drawdown":-0.163133},{"date":"2023-11-03","drawdown":-0.160624},{"date":"2023-11-10","drawdown":-0.13835},{"date":"2023-11-17","drawdown":-0.130767},{"date":"2023-11-24","drawdown":-0.105706},{"date":"2023-12-01","drawdown":-0.11509},{"date":"2023-12-08","drawdown":-0.110173},{"date":"2023-12-14","drawdown":-0.122718},{"date":"2023-12-22","drawdown":-0.116225},{"date":"2023-12-29","drawdown":-0.09653},{"date":"2024-01-05","drawdown":-0.103791},{"date":"2024-01-12","drawdown":-0.109879},{"date":"2024-01-19","drawdown":-0.111079},{"date":"2024-01-26","drawdown":-0.114253},{"date":"2024-02-02","drawdown":-0.103897},{"date":"2024-02-09","drawdown":-0.092326},{"date":"2024-02-16","drawdown":-0.082415},{"date":"2024-02-23","drawdown":-0.051795},{"date":"2024-03-01","drawdown":-0.057552},{"date":"2024-03-08","drawdown":-0.069405},{"date":"2024-03-15","drawdown":-0.067553},{"date":"2024-03-22","drawdown":-0.055145},{"date":"2024-03-28","drawdown":-0.051441},{"date":"2024-04-05","drawdown":-0.065886},{"date":"2024-04-12","drawdown":-0.066627},{"date":"2024-04-19","drawdown":-0.07459},{"date":"2024-04-26","drawdown":-0.068849},{"date":"2024-05-03","drawdown":-0.056256},{"date":"2024-05-10","drawdown":-0.048108},{"date":"2024-05-17","drawdown":-0.039959},{"date":"2024-05-24","drawdown":-0.041255},{"date":"2024-05-31","drawdown":-0.058664},{"date":"2024-06-07","drawdown":-0.033292},{"date":"2024-06-14","drawdown":-0.051811},{"date":"2024-06-21","drawdown":-0.067738},{"date":"2024-06-28","drawdown":-0.04107},{"date":"2024-07-05","drawdown":-0.022736},{"date":"2024-07-12","drawdown":-0.01644},{"date":"2024-07-19","drawdown":-0.037181},{"date":"2024-07-26","drawdown":-0.049034},{"date":"2024-08-02","drawdown":-0.069405},{"date":"2024-08-08","drawdown":-0.05533},{"date":"2024-08-16","drawdown":-0.043848},{"date":"2024-08-23","drawdown":-0.039589},{"date":"2024-08-30","drawdown":-0.046626},{"date":"2024-09-06","drawdown":-0.070886},{"date":"2024-09-13","drawdown":-0.054219},{"date":"2024-09-20","drawdown":-0.052182},{"date":"2024-09-27","drawdown":-0.006069},{"date":"2024-10-04","drawdown":0},{"date":"2024-10-11","drawdown":-0.022283},{"date":"2024-10-18","drawdown":-0.016073},{"date":"2024-10-25","drawdown":-0.030502},{"date":"2024-11-01","drawdown":-0.049863},{"date":"2024-11-08","drawdown":-0.047671},{"date":"2024-11-15","drawdown":-0.050594},{"date":"2024-11-22","drawdown":-0.047489},{"date":"2024-11-29","drawdown":-0.059909},{"date":"2024-12-06","drawdown":-0.03726},{"date":"2024-12-13","drawdown":-0.043105},{"date":"2024-12-20","drawdown":-0.047306},{"date":"2024-12-27","drawdown":-0.0179},{"date":"2025-01-03","drawdown":-0.022831},{"date":"2025-01-09","drawdown":-0.020639},{"date":"2025-01-17","drawdown":-0.023379},{"date":"2025-01-24","drawdown":-0.029041},{"date":"2025-01-31","drawdown":-0.009863},{"date":"2025-02-07","drawdown":-0.005662},{"date":"2025-02-14","drawdown":0},{"date":"2025-02-21","drawdown":-0.000711},{"date":"2025-02-28","drawdown":-0.040726},{"date":"2025-03-07","drawdown":-0.024009},{"date":"2025-03-14","drawdown":-0.031478},{"date":"2025-03-20","drawdown":-0.020452},{"date":"2025-03-28","drawdown":-0.033078},{"date":"2025-04-04","drawdown":-0.070069},{"date":"2025-04-11","drawdown":-0.044994},{"date":"2025-04-17","drawdown":-0.044105},{"date":"2025-04-25","drawdown":-0.019207},{"date":"2025-05-02","drawdown":0},{"date":"2025-05-09","drawdown":-0.015625},{"date":"2025-05-16","drawdown":-0.011421},{"date":"2025-05-23","drawdown":-0.023533},{"date":"2025-05-30","drawdown":-0.025956},{"date":"2025-06-06","drawdown":-0.011248},{"date":"2025-06-13","drawdown":-0.009765},{"date":"2025-06-20","drawdown":-0.007367},{"date":"2025-06-27","drawdown":0},{"date":"2025-07-04","drawdown":-0.006392},{"date":"2025-07-11","drawdown":0},{"date":"2025-07-18","drawdown":-0.003936},{"date":"2025-07-25","drawdown":0},{"date":"2025-08-01","drawdown":0},{"date":"2025-08-08","drawdown":-0.098667},{"date":"2025-08-15","drawdown":-0.095407},{"date":"2025-08-22","drawdown":-0.088148},{"date":"2025-08-29","drawdown":-0.091704},{"date":"2025-09-05","drawdown":-0.087111},{"date":"2025-09-12","drawdown":-0.062815},{"date":"2025-09-19","drawdown":-0.050815},{"date":"2025-09-26","drawdown":-0.059704},{"date":"2025-10-03","drawdown":-0.033333},{"date":"2025-10-10","drawdown":-0.037185},{"date":"2025-10-17","drawdown":-0.029185},{"date":"2025-10-24","drawdown":-0.032871},{"date":"2025-10-31","drawdown":-0.01363},{"date":"2025-11-07","drawdown":-0.03363},{"date":"2025-11-14","drawdown":-0.031407},{"date":"2025-11-21","drawdown":-0.056148},{"date":"2025-11-28","drawdown":-0.046667},{"date":"2025-12-05","drawdown":-0.043556},{"date":"2025-12-12","drawdown":-0.050074},{"date":"2025-12-19","drawdown":-0.062074},{"date":"2025-12-24","drawdown":-0.056},{"date":"2026-01-02","drawdown":-0.036444},{"date":"2026-01-09","drawdown":-0.023556},{"date":"2026-01-16","drawdown":-0.016296},{"date":"2026-01-23","drawdown":-0.016741},{"date":"2026-01-30","drawdown":-0.008442},{"date":"2026-02-06","drawdown":-0.006368},{"date":"2026-02-13","drawdown":-0.010194},{"date":"2026-02-20","drawdown":0},{"date":"2026-02-27","drawdown":-0.011918},{"date":"2026-03-06","drawdown":-0.056754},{"date":"2026-03-13","drawdown":-0.047957},{"date":"2026-03-20","drawdown":-0.053348},{"date":"2026-03-27","drawdown":-0.065551},{"date":"2026-04-02","drawdown":-0.053065},{"date":"2026-04-10","drawdown":-0.014756},{"date":"2026-04-17","drawdown":0},{"date":"2026-04-24","drawdown":0},{"date":"2026-04-30","drawdown":0},{"date":"2026-05-08","drawdown":0}],"ee_isin":"ZAE000289948"}
